Workbook
Name churn1: ' Inputs'!$C$9
Name churn2: ' Inputs'!$D$9
Name churn3: ' Inputs'!$E$9
Name churn4: ' Inputs'!$F$9
Name churn5: ' Inputs'!$G$9
Name churn6: ' Inputs'!$H$9
Name churn7: ' Inputs'!$I$9
Name users_y1: Users!$D$26
Name users_y2: Users!$E$26
Name users_y3: Users!$F$26
Name users_y4: Users!$G$26
Name users_y5: Users!$H$26
Name users_y6: Users!$I$26
Name users_y7: Users!$J$26
Name Weeks: ' Inputs'!$K$2

Sheet Acquisition
B1: =' Inputs'!B3 -> 45292 | C1: =B1+31 -> 45323 | D1: =C1+31 -> 45354 | E1: =D1+31 -> 45385 | F1: =E1+31 -> 45416 | G1: =F1+31 -> 45447 | H1: =G1+31 -> 45478 | I1: =H1+31 -> 45509 | J1: =I1+31 -> 45540 | ... CG1: =CF1+31 -> 47865
B2: =CONCATENATE("Month ", B3) -> Month 1 | C2: =CONCATENATE("Month ", C3) -> Month 2 | D2: =CONCATENATE("Month ", D3) -> Month 3 | E2: =CONCATENATE("Month ", E3) -> Month 4 | F2: =CONCATENATE("Month ", F3) -> Month 5 | G2: =CONCATENATE("Month ", G3) -> Month 6 | H2: =CONCATENATE("Month ", H3) -> Month 7 | I2: =CONCATENATE("Month ", I3) -> Month 8 | ... CG2: =CONCATENATE("Month ", CG3) -> Month 84
B3: 1 | C3: 2 | D3: 3 | E3: 4 | F3: 5 | G3: 6 | H3: 7 | I3: 8 | J3: 9 | K3: 10 | L3: 11 | M3: 12 | N3: 13 | O3: 14 | P3: 15 | Q3: 16 | R3: 17 | S3: 18 | T3: 19 | U3: 20 | V3: 21 | W3: 22 | X3: 23 | Y3: 24 | Z3: 25 | AA3: 26 | AB3: 27 | AC3: 28 | AD3: 29 | AE3: 30 | AF3: 31 | AG3: 32 | AH3: 33 | AI3: 34 | AJ3: 35 | AK3: 36 | AL3: 37 | AM3: 38 | AN3: 39 | AO3: 40 | AP3: 41 | AQ3: 42 | AR3: 43 | AS3: 44 | AT3: 45 | AU3: 46 | AV3: 47 | AW3: 48 | AX3: 49 | AY3: 50 | AZ3: 51 | BA3: 52 | BB3: 53 | BC3: 54 | BD3: 55 | BE3: 56 | BF3: 57 | BG3: 58 | BH3: 59 | BI3: 60 | BJ3: 61 | BK3: 62 | BL3: 63 | BM3: 64 | BN3: 65 | BO3: 66 | BP3: 67 | BQ3: 68 | BR3: 69 | BS3: 70 | BT3: 71 | BU3: 72 | BV3: 73 | BW3: 74 | BX3: 75 | BY3: 76 | BZ3: 77 | CA3: 78 | CB3: 79 | CC3: 80 | CD3: 81 | CE3: 82 | CF3: 83 | CG3: 84
A4: User Account Sign Ups
A5: Marketing Spend | B5: 10000 | C5: 25000 | D5: 25000 | E5: 25000 | F5: 25000 | G5: 25000 | H5: 50000 | I5: 50000 | J5: 50000 | K5: 50000 | L5: 50000 | M5: 50000 | N5: 50000 | O5: 50000 | P5: 50000 | Q5: 50000 | R5: 50000 | S5: 50000 | T5: 50000 | U5: 50000 | V5: 50000 | W5: 50000 | X5: 50000 | Y5: 50000 | Z5: 200000 | AA5: 200000 | AB5: 200000 | AC5: 200000 | AD5: 200000 | AE5: 200000 | AF5: 200000 | AG5: 200000 | AH5: 200000 | AI5: 200000 | AJ5: 200000 | AK5: 200000 | AL5: 200000 | AM5: 200000 | AN5: 200000 | AO5: 200000 | AP5: 200000 | AQ5: 200000 | AR5: 200000 | AS5: 200000 | AT5: 200000 | AU5: 200000 | AV5: 200000 | AW5: 200000 | AX5: 200000 | AY5: 200000 | AZ5: 200000 | BA5: 200000 | BB5: 200000 | BC5: 200000 | BD5: 200000 | BE5: 200000 | BF5: 200000 | BG5: 200000 | BH5: 200000 | BI5: 200000 | BJ5: 200000 | BK5: 200000 | BL5: 200000 | BM5: 200000 | BN5: 200000 | BO5: 200000 | BP5: 200000 | BQ5: 200000 | BR5: 200000 | BS5: 200000 | BT5: 200000 | BU5: 200000 | BV5: 200000 | BW5: 200000 | BX5: 200000 | BY5: 200000 | BZ5: 200000 | CA5: 200000 | CB5: 200000 | CC5: 200000 | CD5: 200000 | CE5: 200000 | CF5: 200000 | CG5: 200000
A6: Paid CAC | B6: 50 | C6: 50 | D6: 50 | E6: 50 | F6: 50 | G6: 50 | H6: 25 | I6: 25 | J6: 25 | K6: 25 | L6: 25 | M6: 25 | N6: 10 | O6: 10 | P6: 10 | Q6: 10 | R6: 10 | S6: 10 | T6: 10 | U6: 10 | V6: 10 | W6: 10 | X6: 10 | Y6: 10 | Z6: 5 | AA6: 5 | AB6: 5 | AC6: 5 | AD6: 5 | AE6: 5 | AF6: 5 | AG6: 5 | AH6: 5 | AI6: 5 | AJ6: 5 | AK6: 5 | AL6: 5 | AM6: 5 | AN6: 5 | AO6: 5 | AP6: 5 | AQ6: 5 | AR6: 5 | AS6: 5 | AT6: 5 | AU6: 5 | AV6: 5 | AW6: 5 | AX6: 5 | AY6: 5 | AZ6: 5 | BA6: 5 | BB6: 5 | BC6: 5 | BD6: 5 | BE6: 5 | BF6: 5 | BG6: 5 | BH6: 5 | BI6: 5 | BJ6: 5 | BK6: 5 | BL6: 5 | BM6: 5 | BN6: 5 | BO6: 5 | BP6: 5 | BQ6: 5 | BR6: 5 | BS6: 5 | BT6: 5 | BU6: 5 | BV6: 5 | BW6: 5 | BX6: 5 | BY6: 5 | BZ6: 5 | CA6: 5 | CB6: 5 | CC6: 5 | CD6: 5 | CE6: 5 | CF6: 5 | CG6: 5
A7: New Users (Paid) | B7: =B5/B6 -> 200 | C7: =C5/C6 -> 500 | D7: =D5/D6 -> 500 | E7: =E5/E6 -> 500 | F7: =F5/F6 -> 500 | G7: =G5/G6 -> 500 | H7: =H5/H6 -> 2000 | I7: =I5/I6 -> 2000 | ... CG7: =CG5/CG6 -> 40000
A8: Organic : Paid Ratio | B8: 5 | C8: 5 | D8: 5 | E8: 5 | F8: 5 | G8: 5 | H8: 5 | I8: 5 | J8: 5 | K8: 5 | L8: 5 | M8: 5 | N8: 10 | O8: 10 | P8: 10 | Q8: 10 | R8: 10 | S8: 10 | T8: 10 | U8: 10 | V8: 10 | W8: 10 | X8: 10 | Y8: 10 | Z8: 10 | AA8: 10 | AB8: 10 | AC8: 10 | AD8: 10 | AE8: 10 | AF8: 10 | AG8: 10 | AH8: 10 | AI8: 10 | AJ8: 10 | AK8: 10 | AL8: 10 | AM8: 10 | AN8: 10 | AO8: 10 | AP8: 10 | AQ8: 10 | AR8: 10 | AS8: 10 | AT8: 10 | AU8: 10 | AV8: 10 | AW8: 10 | AX8: 10 | AY8: 10 | AZ8: 10 | BA8: 10 | BB8: 10 | BC8: 10 | BD8: 10 | BE8: 10 | BF8: 10 | BG8: 10 | BH8: 10 | BI8: 10 | BJ8: 10 | BK8: 10 | BL8: 10 | BM8: 10 | BN8: 10 | BO8: 10 | BP8: 10 | BQ8: 10 | BR8: 10 | BS8: 10 | BT8: 10 | BU8: 10 | BV8: 10 | BW8: 10 | BX8: 10 | BY8: 10 | BZ8: 10 | CA8: 10 | CB8: 10 | CC8: 10 | CD8: 10 | CE8: 10 | CF8: 10 | CG8: 10
A9: New Users (Organic) | B9: =B7*B8 -> 1000 | C9: =C7*C8 -> 2500 | D9: =D7*D8 -> 2500 | E9: =E7*E8 -> 2500 | F9: =F7*F8 -> 2500 | G9: =G7*G8 -> 2500 | H9: =H7*H8 -> 10000 | I9: =I7*I8 -> 10000 | ... CG9: =CG7*CG8 -> 400000
A10: Total New Users | B10: =B7+B9 -> 1200 | C10: =C7+C9 -> 3000 | D10: =D7+D9 -> 3000 | E10: =E7+E9 -> 3000 | F10: =F7+F9 -> 3000 | G10: =G7+G9 -> 3000 | H10: =H7+H9 -> 12000 | I10: =I7+I9 -> 12000 | ... CG10: =CG7+CG9 -> 440000
A12: Churn Rate for Users | B12: 0.05 | C12: 0.05 | D12: 0.05 | E12: 0.05 | F12: 0.05 | G12: 0.05 | H12: 0.05 | I12: 0.05 | J12: 0.05 | K12: 0.05 | L12: 0.05 | M12: 0.05 | N12: 0.05 | O12: 0.05 | P12: 0.05 | Q12: 0.05 | R12: 0.05 | S12: 0.05 | T12: 0.05 | U12: 0.05 | V12: 0.05 | W12: 0.05 | X12: 0.05 | Y12: 0.05 | Z12: 0.05 | AA12: 0.05 | AB12: 0.05 | AC12: 0.05 | AD12: 0.05 | AE12: 0.05 | AF12: 0.05 | AG12: 0.05 | AH12: 0.05 | AI12: 0.05 | AJ12: 0.05 | AK12: 0.05 | AL12: 0.05 | AM12: 0.05 | AN12: 0.05 | AO12: 0.05 | AP12: 0.05 | AQ12: 0.05 | AR12: 0.05 | AS12: 0.05 | AT12: 0.05 | AU12: 0.05 | AV12: 0.05 | AW12: 0.05 | AX12: 0.05 | AY12: 0.05 | AZ12: 0.05 | BA12: 0.05 | BB12: 0.05 | BC12: 0.05 | BD12: 0.05 | BE12: 0.05 | BF12: 0.05 | BG12: 0.05 | BH12: 0.05 | BI12: 0.05 | BJ12: 0.05 | BK12: 0.05 | BL12: 0.05 | BM12: 0.05 | BN12: 0.05 | BO12: 0.05 | BP12: 0.05 | BQ12: 0.05 | BR12: 0.05 | BS12: 0.05 | BT12: 0.05 | BU12: 0.05 | BV12: 0.05 | BW12: 0.05 | BX12: 0.05 | BY12: 0.05 | BZ12: 0.05 | CA12: 0.05 | CB12: 0.05 | CC12: 0.05 | CD12: 0.05 | CE12: 0.05 | CF12: 0.05 | CG12: 0.05
A13: Churned Users | B13: =B10*B12 -> 60 | C13: =C10*C12 -> 150 | D13: =D10*D12 -> 150 | E13: =E10*E12 -> 150 | F13: =F10*F12 -> 150 | G13: =G10*G12 -> 150 | H13: =H10*H12 -> 600 | I13: =I10*I12 -> 600 | ... CG13: =CG10*CG12 -> 22000
A15: Total Monthly Active Users (MAU) | B15: =B10-B13 -> 1140 | C15: =B15+C10-C13 -> 3990 | D15: =C15+D10-D13 -> 6840 | E15: =D15+E10-E13 -> 9690 | F15: =E15+F10-F13 -> 12540 | G15: =F15+G10-G13 -> 15390 | H15: =G15+H10-H13 -> 26790 | I15: =H15+I10-I13 -> 38190 | J15: =I15+J10-J13 -> 49590 | ... CG15: =CF15+CG10-CG13 -> 25790790
A17: Average Log Ins (sessions) / Month | B17: 20 | C17: 20 | D17: 20 | E17: 20 | F17: 20 | G17: 20 | H17: 20 | I17: 20 | J17: 20 | K17: 20 | L17: 20 | M17: 20 | N17: 20 | O17: 20 | P17: 20 | Q17: 20 | R17: 20 | S17: 20 | T17: 20 | U17: 20 | V17: 20 | W17: 20 | X17: 20 | Y17: 20 | Z17: 25 | AA17: 25 | AB17: 25 | AC17: 25 | AD17: 25 | AE17: 25 | AF17: 25 | AG17: 25 | AH17: 25 | AI17: 25 | AJ17: 25 | AK17: 25 | AL17: 25 | AM17: 25 | AN17: 25 | AO17: 25 | AP17: 25 | AQ17: 25 | AR17: 25 | AS17: 25 | AT17: 25 | AU17: 25 | AV17: 25 | AW17: 25 | AX17: 25 | AY17: 25 | AZ17: 25 | BA17: 25 | BB17: 25 | BC17: 25 | BD17: 25 | BE17: 25 | BF17: 25 | BG17: 25 | BH17: 25 | BI17: 25 | BJ17: 25 | BK17: 25 | BL17: 25 | BM17: 25 | BN17: 25 | BO17: 25 | BP17: 25 | BQ17: 25 | BR17: 25 | BS17: 25 | BT17: 25 | BU17: 25 | BV17: 25 | BW17: 25 | BX17: 25 | BY17: 25 | BZ17: 25 | CA17: 25 | CB17: 25 | CC17: 25 | CD17: 25 | CE17: 25 | CF17: 25 | CG17: 25
A18: Average Session Time (minutes) | B18: 5 | C18: 5 | D18: 5 | E18: 5 | F18: 5 | G18: 5 | H18: 5 | I18: 5 | J18: 5 | K18: 5 | L18: 5 | M18: 5 | N18: 10 | O18: 10 | P18: 10 | Q18: 10 | R18: 10 | S18: 10 | T18: 10 | U18: 10 | V18: 10 | W18: 10 | X18: 10 | Y18: 10 | Z18: 15 | AA18: 15 | AB18: 15 | AC18: 15 | AD18: 15 | AE18: 15 | AF18: 15 | AG18: 15 | AH18: 15 | AI18: 15 | AJ18: 15 | AK18: 15 | AL18: 20 | AM18: 20 | AN18: 20 | AO18: 20 | AP18: 20 | AQ18: 20 | AR18: 20 | AS18: 20 | AT18: 20 | AU18: 20 | AV18: 20 | AW18: 20 | AX18: 20 | AY18: 20 | AZ18: 20 | BA18: 20 | BB18: 20 | BC18: 20 | BD18: 20 | BE18: 20 | BF18: 20 | BG18: 20 | BH18: 20 | BI18: 20 | BJ18: 20 | BK18: 20 | BL18: 20 | BM18: 20 | BN18: 20 | BO18: 20 | BP18: 20 | BQ18: 20 | BR18: 20 | BS18: 20 | BT18: 20 | BU18: 20 | BV18: 20 | BW18: 20 | BX18: 20 | BY18: 20 | BZ18: 20 | CA18: 20 | CB18: 20 | CC18: 20 | CD18: 20 | CE18: 20 | CF18: 20 | CG18: 20
A19: Ad Impressions / Minute (ad load) | B19: 0.1 | C19: 0.1 | D19: 0.1 | E19: 0.1 | F19: 0.1 | G19: 0.1 | H19: 0.1 | I19: 0.1 | J19: 0.1 | K19: 0.1 | L19: 0.1 | M19: 0.1 | N19: 0.1 | O19: 0.1 | P19: 0.1 | Q19: 0.1 | R19: 0.1 | S19: 0.1 | T19: 0.1 | U19: 0.1 | V19: 0.1 | W19: 0.1 | X19: 0.1 | Y19: 0.1 | Z19: 0.1 | AA19: 0.1 | AB19: 0.1 | AC19: 0.1 | AD19: 0.1 | AE19: 0.1 | AF19: 0.1 | AG19: 0.1 | AH19: 0.1 | AI19: 0.1 | AJ19: 0.1 | AK19: 0.1 | AL19: 0.1 | AM19: 0.1 | AN19: 0.1 | AO19: 0.1 | AP19: 0.1 | AQ19: 0.1 | AR19: 0.1 | AS19: 0.1 | AT19: 0.1 | AU19: 0.1 | AV19: 0.1 | AW19: 0.1 | AX19: 0.1 | AY19: 0.1 | AZ19: 0.1 | BA19: 0.1 | BB19: 0.1 | BC19: 0.1 | BD19: 0.1 | BE19: 0.1 | BF19: 0.1 | BG19: 0.1 | BH19: 0.1 | BI19: 0.1 | BJ19: 0.1 | BK19: 0.1 | BL19: 0.1 | BM19: 0.1 | BN19: 0.1 | BO19: 0.1 | BP19: 0.1 | BQ19: 0.1 | BR19: 0.1 | BS19: 0.1 | BT19: 0.1 | BU19: 0.1 | BV19: 0.1 | BW19: 0.1 | BX19: 0.1 | BY19: 0.1 | BZ19: 0.1 | CA19: 0.1 | CB19: 0.1 | CC19: 0.1 | CD19: 0.1 | CE19: 0.1 | CF19: 0.1 | CG19: 0.1
A20: Ads Shows / User / Month | B20: =B17*B18*B19 -> 10 | C20: =C17*C18*C19 -> 10 | D20: =D17*D18*D19 -> 10 | E20: =E17*E18*E19 -> 10 | F20: =F17*F18*F19 -> 10 | G20: =G17*G18*G19 -> 10 | H20: =H17*H18*H19 -> 10 | I20: =I17*I18*I19 -> 10 | ... CG20: =CG17*CG18*CG19 -> 50
A22: CPM (cost per 1,000 ad impressions) | B22: 0 | C22: 0 | D22: 0 | E22: 0 | F22: 0 | G22: 0 | H22: 0 | I22: 0 | J22: 0 | K22: 0 | L22: 0 | M22: 0 | N22: 10 | O22: 10 | P22: 10 | Q22: 10 | R22: 10 | S22: 10 | T22: 10 | U22: 10 | V22: 10 | W22: 10 | X22: 10 | Y22: 10 | Z22: 10 | AA22: 10 | AB22: 10 | AC22: 10 | AD22: 10 | AE22: 10 | AF22: 10 | AG22: 10 | AH22: 10 | AI22: 10 | AJ22: 10 | AK22: 10 | AL22: 10 | AM22: 10 | AN22: 10 | AO22: 10 | AP22: 10 | AQ22: 10 | AR22: 10 | AS22: 10 | AT22: 10 | AU22: 10 | AV22: 10 | AW22: 10 | AX22: 10 | AY22: 10 | AZ22: 10 | BA22: 10 | BB22: 10 | BC22: 10 | BD22: 10 | BE22: 10 | BF22: 10 | BG22: 10 | BH22: 10 | BI22: 10 | BJ22: 10 | BK22: 10 | BL22: 10 | BM22: 10 | BN22: 10 | BO22: 10 | BP22: 10 | BQ22: 10 | BR22: 10 | BS22: 10 | BT22: 10 | BU22: 10 | BV22: 10 | BW22: 10 | BX22: 10 | BY22: 10 | BZ22: 10 | CA22: 10 | CB22: 10 | CC22: 10 | CD22: 10 | CE22: 10 | CF22: 10 | CG22: 10
A24: Revenue / Ad | B24: =B22/1000 -> 0 | C24: =C22/1000 -> 0 | D24: =D22/1000 -> 0 | E24: =E22/1000 -> 0 | F24: =F22/1000 -> 0 | G24: =G22/1000 -> 0 | H24: =H22/1000 -> 0 | I24: =I22/1000 -> 0 | ... CG24: =CG22/1000 -> 0.01
A25: Monthly Revenue / User | B25: =B20*B24 -> 0 | C25: =C20*C24 -> 0 | D25: =D20*D24 -> 0 | E25: =E20*E24 -> 0 | F25: =F20*F24 -> 0 | G25: =G20*G24 -> 0 | H25: =H20*H24 -> 0 | I25: =I20*I24 -> 0 | ... CG25: =CG20*CG24 -> 0.5
A26: Annual Revenue / User | B26: =B25*12 -> 0 | C26: =C25*12 -> 0 | D26: =D25*12 -> 0 | E26: =E25*12 -> 0 | F26: =F25*12 -> 0 | G26: =G25*12 -> 0 | H26: =H25*12 -> 0 | I26: =I25*12 -> 0 | ... CG26: =CG25*12 -> 6
A28: Total Ad Revenue | B28: =B15*B25 -> 0 | C28: =C15*C25 -> 0 | D28: =D15*D25 -> 0 | E28: =E15*E25 -> 0 | F28: =F15*F25 -> 0 | G28: =G15*G25 -> 0 | H28: =H15*H25 -> 0 | I28: =I15*I25 -> 0 | ... CG28: =CG15*CG25 -> 12895395
A30: Pro Account Sign Ups
A31: Marketing Spend | B31: 15000 | C31: 15000 | D31: 15000 | E31: 15000 | F31: 15000 | G31: 15000 | H31: 15000 | I31: 15000 | J31: 15000 | K31: 15000 | L31: 15000 | M31: 15000 | N31: 15000 | O31: 15000 | P31: 15000 | Q31: 15000 | R31: 15000 | S31: 15000 | T31: 15000 | U31: 15000 | V31: 15000 | W31: 15000 | X31: 15000 | Y31: 15000 | Z31: 15000 | AA31: 15000 | AB31: 15000 | AC31: 15000 | AD31: 15000 | AE31: 15000 | AF31: 15000 | AG31: 15000 | AH31: 15000 | AI31: 15000 | AJ31: 15000 | AK31: 15000 | AL31: 15000 | AM31: 15000 | AN31: 15000 | AO31: 15000 | AP31: 15000 | AQ31: 15000 | AR31: 15000 | AS31: 15000 | AT31: 15000 | AU31: 15000 | AV31: 15000 | AW31: 15000 | AX31: 15000 | AY31: 15000 | AZ31: 15000 | BA31: 15000 | BB31: 15000 | BC31: 15000 | BD31: 15000 | BE31: 15000 | BF31: 15000 | BG31: 15000 | BH31: 15000 | BI31: 15000 | BJ31: 15000 | BK31: 15000 | BL31: 15000 | BM31: 15000 | BN31: 15000 | BO31: 15000 | BP31: 15000 | BQ31: 15000 | BR31: 15000 | BS31: 15000 | BT31: 15000 | BU31: 15000 | BV31: 15000 | BW31: 15000 | BX31: 15000 | BY31: 15000 | BZ31: 15000 | CA31: 15000 | CB31: 15000 | CC31: 15000 | CD31: 15000 | CE31: 15000 | CF31: 15000 | CG31: 15000
A32: Paid CAC | B32: 100 | C32: 100 | D32: 100 | E32: 100 | F32: 100 | G32: 100 | H32: 100 | I32: 100 | J32: 100 | K32: 100 | L32: 100 | M32: 100 | N32: 100 | O32: 100 | P32: 100 | Q32: 100 | R32: 100 | S32: 100 | T32: 100 | U32: 100 | V32: 100 | W32: 100 | X32: 100 | Y32: 100 | Z32: 100 | AA32: 100 | AB32: 100 | AC32: 100 | AD32: 100 | AE32: 100 | AF32: 100 | AG32: 100 | AH32: 100 | AI32: 100 | AJ32: 100 | AK32: 100 | AL32: 100 | AM32: 100 | AN32: 100 | AO32: 100 | AP32: 100 | AQ32: 100 | AR32: 100 | AS32: 100 | AT32: 100 | AU32: 100 | AV32: 100 | AW32: 100 | AX32: 100 | AY32: 100 | AZ32: 100 | BA32: 100 | BB32: 100 | BC32: 100 | BD32: 100 | BE32: 100 | BF32: 100 | BG32: 100 | BH32: 100 | BI32: 100 | BJ32: 100 | BK32: 100 | BL32: 100 | BM32: 100 | BN32: 100 | BO32: 100 | BP32: 100 | BQ32: 100 | BR32: 100 | BS32: 100 | BT32: 100 | BU32: 100 | BV32: 100 | BW32: 100 | BX32: 100 | BY32: 100 | BZ32: 100 | CA32: 100 | CB32: 100 | CC32: 100 | CD32: 100 | CE32: 100 | CF32: 100 | CG32: 100
A33: New Pros (Paid) | B33: =B31/B32 -> 150 | C33: =C31/C32 -> 150 | D33: =D31/D32 -> 150 | E33: =E31/E32 -> 150 | F33: =F31/F32 -> 150 | G33: =G31/G32 -> 150 | H33: =H31/H32 -> 150 | I33: =I31/I32 -> 150 | ... CG33: =CG31/CG32 -> 150
A34: Organic : Paid Ratio | B34: 0.2 | C34: 0.2 | D34: 0.2 | E34: 0.2 | F34: 0.2 | G34: 0.2 | H34: 0.2 | I34: 0.2 | J34: 0.2 | K34: 0.2 | L34: 0.2 | M34: 0.2 | N34: 0.2 | O34: 0.2 | P34: 0.2 | Q34: 0.2 | R34: 0.2 | S34: 0.2 | T34: 0.2 | U34: 0.2 | V34: 0.2 | W34: 0.2 | X34: 0.2 | Y34: 0.2 | Z34: 0.2 | AA34: 0.2 | AB34: 0.2 | AC34: 0.2 | AD34: 0.2 | AE34: 0.2 | AF34: 0.2 | AG34: 0.2 | AH34: 0.2 | AI34: 0.2 | AJ34: 0.2 | AK34: 0.2 | AL34: 0.2 | AM34: 0.2 | AN34: 0.2 | AO34: 0.2 | AP34: 0.2 | AQ34: 0.2 | AR34: 0.2 | AS34: 0.2 | AT34: 0.2 | AU34: 0.2 | AV34: 0.2 | AW34: 0.2 | AX34: 0.2 | AY34: 0.2 | AZ34: 0.2 | BA34: 0.2 | BB34: 0.2 | BC34: 0.2 | BD34: 0.2 | BE34: 0.2 | BF34: 0.2 | BG34: 0.2 | BH34: 0.2 | BI34: 0.2 | BJ34: 0.2 | BK34: 0.2 | BL34: 0.2 | BM34: 0.2 | BN34: 0.2 | BO34: 0.2 | BP34: 0.2 | BQ34: 0.2 | BR34: 0.2 | BS34: 0.2 | BT34: 0.2 | BU34: 0.2 | BV34: 0.2 | BW34: 0.2 | BX34: 0.2 | BY34: 0.2 | BZ34: 0.2 | CA34: 0.2 | CB34: 0.2 | CC34: 0.2 | CD34: 0.2 | CE34: 0.2 | CF34: 0.2 | CG34: 0.2
A35: New Pros (Organic) | B35: =B34*B33 -> 30 | C35: =C34*C33 -> 30 | D35: =D34*D33 -> 30 | E35: =E34*E33 -> 30 | F35: =F34*F33 -> 30 | G35: =G34*G33 -> 30 | H35: =H34*H33 -> 30 | I35: =I34*I33 -> 30 | ... CG35: =CG34*CG33 -> 30
A36: Total New Pro Accounts | B36: =B35+B33 -> 180 | C36: =C35+C33 -> 180 | D36: =D35+D33 -> 180 | E36: =E35+E33 -> 180 | F36: =F35+F33 -> 180 | G36: =G35+G33 -> 180 | H36: =H35+H33 -> 180 | I36: =I35+I33 -> 180 | ... CG36: =CG35+CG33 -> 180
A38: Churn Rate for Pros | B38: 0.2 | C38: 0.2 | D38: 0.2 | E38: 0.2 | F38: 0.2 | G38: 0.2 | H38: 0.2 | I38: 0.2 | J38: 0.2 | K38: 0.2 | L38: 0.2 | M38: 0.2 | N38: 0.1 | O38: 0.1 | P38: 0.1 | Q38: 0.1 | R38: 0.1 | S38: 0.1 | T38: 0.1 | U38: 0.1 | V38: 0.1 | W38: 0.1 | X38: 0.1 | Y38: 0.1 | Z38: 0.1 | AA38: 0.1 | AB38: 0.1 | AC38: 0.1 | AD38: 0.1 | AE38: 0.1 | AF38: 0.1 | AG38: 0.1 | AH38: 0.1 | AI38: 0.1 | AJ38: 0.1 | AK38: 0.1 | AL38: 0.1 | AM38: 0.1 | AN38: 0.1 | AO38: 0.1 | AP38: 0.1 | AQ38: 0.1 | AR38: 0.1 | AS38: 0.1 | AT38: 0.1 | AU38: 0.1 | AV38: 0.1 | AW38: 0.1 | AX38: 0.1 | AY38: 0.1 | AZ38: 0.1 | BA38: 0.1 | BB38: 0.1 | BC38: 0.1 | BD38: 0.1 | BE38: 0.1 | BF38: 0.1 | BG38: 0.1 | BH38: 0.1 | BI38: 0.1 | BJ38: 0.1 | BK38: 0.1 | BL38: 0.1 | BM38: 0.1 | BN38: 0.1 | BO38: 0.1 | BP38: 0.1 | BQ38: 0.1 | BR38: 0.1 | BS38: 0.1 | BT38: 0.1 | BU38: 0.1 | BV38: 0.1 | BW38: 0.1 | BX38: 0.1 | BY38: 0.1 | BZ38: 0.1 | CA38: 0.1 | CB38: 0.1 | CC38: 0.1 | CD38: 0.1 | CE38: 0.1 | CF38: 0.1 | CG38: 0.1
A39: Churned Pro Accounts | B39: =B36*B38 -> 36 | C39: =C36*C38 -> 36 | D39: =D36*D38 -> 36 | E39: =E36*E38 -> 36 | F39: =F36*F38 -> 36 | G39: =G36*G38 -> 36 | H39: =H36*H38 -> 36 | I39: =I36*I38 -> 36 | ... CG39: =CG36*CG38 -> 18
A41: Total Monthly Active Pros | B41: =B36-B39 -> 144 | C41: =B41+C36-C39 -> 288 | D41: =C41+D36-D39 -> 432 | E41: =D41+E36-E39 -> 576 | F41: =E41+F36-F39 -> 720 | G41: =F41+G36-G39 -> 864 | H41: =G41+H36-H39 -> 1008 | I41: =H41+I36-I39 -> 1152 | J41: =I41+J36-J39 -> 1296 | ... CG41: =CF41+CG36-CG39 -> 13392
A43: Avg Pro Subscription / Month | B43: 0 | C43: 0 | D43: 0 | E43: 0 | F43: 0 | G43: 0 | H43: 0 | I43: 0 | J43: 0 | K43: 0 | L43: 0 | M43: 0 | N43: 10 | O43: 10 | P43: 10 | Q43: 10 | R43: 10 | S43: 10 | T43: 10 | U43: 10 | V43: 10 | W43: 10 | X43: 10 | Y43: 10 | Z43: 25 | AA43: 25 | AB43: 25 | AC43: 25 | AD43: 25 | AE43: 25 | AF43: 25 | AG43: 25 | AH43: 25 | AI43: 25 | AJ43: 25 | AK43: 25 | AL43: 25 | AM43: 25 | AN43: 25 | AO43: 25 | AP43: 25 | AQ43: 25 | AR43: 25 | AS43: 25 | AT43: 25 | AU43: 25 | AV43: 25 | AW43: 25 | AX43: 25 | AY43: 25 | AZ43: 25 | BA43: 25 | BB43: 25 | BC43: 25 | BD43: 25 | BE43: 25 | BF43: 25 | BG43: 25 | BH43: 25 | BI43: 25 | BJ43: 25 | BK43: 25 | BL43: 25 | BM43: 25 | BN43: 25 | BO43: 25 | BP43: 25 | BQ43: 25 | BR43: 25 | BS43: 25 | BT43: 25 | BU43: 25 | BV43: 25 | BW43: 25 | BX43: 25 | BY43: 25 | BZ43: 25 | CA43: 25 | CB43: 25 | CC43: 25 | CD43: 25 | CE43: 25 | CF43: 25 | CG43: 25
A44: % Paid Subsriptions | B44: 0 | C44: 0 | D44: 0 | E44: 0 | F44: 0 | G44: 0 | H44: 0 | I44: 0 | J44: 0 | K44: 0 | L44: 0 | M44: 0 | N44: 0.2 | O44: 0.2 | P44: 0.2 | Q44: 0.2 | R44: 0.2 | S44: 0.2 | T44: 0.2 | U44: 0.2 | V44: 0.2 | W44: 0.2 | X44: 0.2 | Y44: 0.2 | Z44: 0.2 | AA44: 0.2 | AB44: 0.2 | AC44: 0.2 | AD44: 0.2 | AE44: 0.2 | AF44: 0.2 | AG44: 0.2 | AH44: 0.2 | AI44: 0.2 | AJ44: 0.2 | AK44: 0.2 | AL44: 0.2 | AM44: 0.2 | AN44: 0.2 | AO44: 0.2 | AP44: 0.2 | AQ44: 0.2 | AR44: 0.2 | AS44: 0.2 | AT44: 0.2 | AU44: 0.2 | AV44: 0.2 | AW44: 0.2 | AX44: 0.2 | AY44: 0.2 | AZ44: 0.2 | BA44: 0.2 | BB44: 0.2 | BC44: 0.2 | BD44: 0.2 | BE44: 0.2 | BF44: 0.2 | BG44: 0.2 | BH44: 0.2 | BI44: 0.2 | BJ44: 0.2 | BK44: 0.2 | BL44: 0.2 | BM44: 0.2 | BN44: 0.2 | BO44: 0.2 | BP44: 0.2 | BQ44: 0.2 | BR44: 0.2 | BS44: 0.2 | BT44: 0.2 | BU44: 0.2 | BV44: 0.2 | BW44: 0.2 | BX44: 0.2 | BY44: 0.2 | BZ44: 0.2 | CA44: 0.2 | CB44: 0.2 | CC44: 0.2 | CD44: 0.2 | CE44: 0.2 | CF44: 0.2 | CG44: 0.2
A45: Free Pro Accounts | B45: =B41*(1-B44) -> 144 | C45: =C41*(1-C44) -> 288 | D45: =D41*(1-D44) -> 432 | E45: =E41*(1-E44) -> 576 | F45: =F41*(1-F44) -> 720 | G45: =G41*(1-G44) -> 864 | H45: =H41*(1-H44) -> 1008 | I45: =I41*(1-I44) -> 1152 | ... CG45: =CG41*(1-CG44) -> 10713.6
A46: Paid Pro Accounts | B46: =B41*B44 -> 0 | C46: =C41*C44 -> 0 | D46: =D41*D44 -> 0 | E46: =E41*E44 -> 0 | F46: =F41*F44 -> 0 | G46: =G41*G44 -> 0 | H46: =H41*H44 -> 0 | I46: =I41*I44 -> 0 | ... CG46: =CG41*CG44 -> 2678.4
A48: Subscription Revenue | B48: =B43*B46 -> 0 | C48: =C43*C46 -> 0 | D48: =D43*D46 -> 0 | E48: =E43*E46 -> 0 | F48: =F43*F46 -> 0 | G48: =G43*G46 -> 0 | H48: =H43*H46 -> 0 | I48: =I43*I46 -> 0 | ... CG48: =CG43*CG46 -> 66960
A50: TOTAL REVENUE | B50: =B28+B48 -> 0 | C50: =C28+C48 -> 0 | D50: =D28+D48 -> 0 | E50: =E28+E48 -> 0 | F50: =F28+F48 -> 0 | G50: =G28+G48 -> 0 | H50: =H28+H48 -> 0 | I50: =I28+I48 -> 0 | ... CG50: =CG28+CG48 -> 12962355

Sheet  Inputs
B1: Year 0 | C1: Year 1 | D1: Year 2 | E1: Year 3 | F1: Year 4 | G1: Year 5 | H1: Year 6 | I1: Year 7
A3: Starting Month | B3: 45292
A5: Businesses
A6: Business Acquistion Cost | C6: 50 | D6: 50 | E6: 50 | F6: 50 | G6: 50 | H6: 50 | I6: 50
A7: % Organic Acquisition | C7: 0.05 | D7: 0.25 | E7: 0.5 | F7: 0.5 | G7: 0.5 | H7: 0.5 | I7: 0.5
A8: Business Signups (MoM) | C8: 0.1 | D8: 0.1 | E8: 0.12 | F8: 0.15 | G8: 0.15 | H8: 0.15 | I8: 0.15
A9: Monthly Churn | C9: 0.05 | D9: 0.05 | E9: 0.05 | F9: 0.05 | G9: 0.05 | H9: 0.05 | I9: 0.05
A12: Customers
A13: Customer acquistion cost | C13: 20 | D13: 15 | E13: 10 | F13: 10 | G13: 10 | H13: 10 | I13: 10
A14: % Organic acquisition | C14: 0.2 | D14: 0.3 | E14: 0.3 | F14: 0.4 | G14: 0.5 | H14: 0.5 | I14: 0.5
A15: Customer churn | C15: 0.05 | D15: 0.05 | E15: 0.05 | F15: 0.05 | G15: 0.05 | H15: 0.05 | I15: 0.05
A18: Ticketing
A19: Average Ticket | C19: =AVERAGE(#REF!) -> #REF! | D19: =AVERAGE(#REF!) -> #REF! | E19: =AVERAGE(#REF!) -> #REF! | F19: =AVERAGE(#REF!) -> #REF! | G19: =AVERAGE(#REF!) -> #REF! | H19: =AVERAGE(#REF!) -> #REF! | I19: =AVERAGE(#REF!) -> #REF!
A20: Nigh per ticket fee | C20: 1.25 | D20: 1.25 | E20: 1.25 | F20: 1.5 | G20: 1.5 | H20: 1.5 | I20: 1.75
A21: Stripe per ticket fee | C21: 0.3 | D21: 0.3 | E21: 0.3 | F21: 0.2 | G21: 0.2 | H21: 0.2 | I21: 0.2
A22: Net Nigh ticket fee | C22: =C20-C21 -> 0.95 | D22: =D20-D21 -> 0.95 | E22: =E20-E21 -> 0.95 | F22: =F20-F21 -> 1.3 | G22: =G20-G21 -> 1.3 | H22: =H20-H21 -> 1.3 | I22: =I20-I21 -> 1.55
A24: Nigh transaction fee | C24: 0.035 | D24: 0.035 | E24: 0.035 | F24: 0.035 | G24: 0.035 | H24: 0.035 | I24: 0.035
A25: Stripe credit card fee | C25: 0.029 | D25: 0.029 | E25: 0.029 | F25: 0.025 | G25: 0.025 | H25: 0.02 | I25: 0.02
A26: Net Nigh transaction fee | C26: =C24-C25 -> 0.006 | D26: =D24-D25 -> 0.006 | E26: =E24-E25 -> 0.006 | F26: =F24-F25 -> 0.01 | G26: =G24-G25 -> 0.01 | H26: =H24-H25 -> 0.015 | I26: =I24-I25 -> 0.015
A28: Business Subscriptions
A29: Avg Montly $ Per Biz | C29: 0 | D29: 25 | E29: 50 | F29: 100 | G29: 100 | H29: 100 | I29: 100
A30: % of Businesses Subscribed | C30: 0 | D30: 0.25 | E30: 0.3 | F30: 0.35 | G30: 0.4 | H30: 0.45 | I30: 0.5
A32: Ad/Boost revenue
A33: % of videos boosted | C33: 0 | D33: 0 | E33: 0.1 | F33: 0.1 | G33: 0.1 | H33: 0.1 | I33: 0.1
A34: Avg price per impression | C34: 0 | D34: 0 | E34: 1.5 | F34: 1.5 | G34: 1.5 | H34: 2 | I34: 2
A35: Impression per Customer
A37: Customer Subscriptions
A38: Avg Monthly $ Per Customer | C38: 0 | D38: 5 | E38: 5 | F38: 5 | G38: 5 | H38: 7 | I38: 7
A39: % of Customers Subscribed | C39: 0 | D39: 0 | E39: 0 | F39: 0 | G39: 0 | H39: 0 | I39: 0
A41: Influencer Subscriptions
A42: Avg Monthly $ Per Influencer | C42: 0 | D42: 0 | E42: 5 | F42: 5 | G42: 5 | H42: 7 | I42: 7
A43: % Influencers to Customers Ratio | C43: 0 | D43: 0 | E43: 0.0025 | F43: 0.005 | G43: 0.005 | H43: 0.0075 | I43: 0.0075
A44: % of Infuencers Subscribed | C44: 0 | D44: 0 | E44: 0 | F44: 0 | G44: 0 | H44: 0 | I44: 0
A47: Expenses
A48: Annual Escalator | C48: %
A49: Year 2 | C49: 0.1
A50: Year 3 | C50: 0.1
A51: Year 4 | C51: 0.1
A52: Year 5 | C52: 0.1
A53: Year 6 | C53: 0.1
A54: Year 7 | C54: 0.1
A56: Variable of Revenue | C56: %
A57: Year 1 | C57: 0
A58: Year 2 | C58: 0
A59: Year 3 | C59: 0
A60: Year 4 | C60: =10% -> 0.1
A61: Year 5 | C61: 0.15
A62: Year 6 | C62: 0.15
A63: Year 7 | C63: 0.15

Sheet Summary
B1: 2024 | C1: 2025 | D1: 2026 | E1: 2027 | F1: 2028 | G1: 2029 | H1: 2030 | J1: =' Inputs'!B3 -> 45292 | K1: =J1+31 -> 45323 | L1: =K1+31 -> 45354 | M1: =L1+31 -> 45385 | N1: =M1+31 -> 45416 | O1: =N1+31 -> 45447 | P1: =O1+31 -> 45478 | Q1: =P1+31 -> 45509 | R1: =Q1+31 -> 45540 | ... CO1: =CN1+31 -> 47865
B2: Year 1 | C2: Year 2 | D2: Year 3 | E2: Year 4 | F2: Year 5 | G2: Year 6 | H2: Year 7 | J2: =CONCATENATE("Month ", J3) -> Month 1 | K2: =CONCATENATE("Month ", K3) -> Month 2 | L2: =CONCATENATE("Month ", L3) -> Month 3 | M2: =CONCATENATE("Month ", M3) -> Month 4 | N2: =CONCATENATE("Month ", N3) -> Month 5 | O2: =CONCATENATE("Month ", O3) -> Month 6 | P2: =CONCATENATE("Month ", P3) -> Month 7 | Q2: =CONCATENATE("Month ", Q3) -> Month 8 | ... CO2: =CONCATENATE("Month ", CO3) -> Month 84
J3: 1 | K3: 2 | L3: 3 | M3: 4 | N3: 5 | O3: 6 | P3: 7 | Q3: 8 | R3: 9 | S3: 10 | T3: 11 | U3: 12 | V3: 13 | W3: 14 | X3: 15 | Y3: 16 | Z3: 17 | AA3: 18 | AB3: 19 | AC3: 20 | AD3: 21 | AE3: 22 | AF3: 23 | AG3: 24 | AH3: 25 | AI3: 26 | AJ3: 27 | AK3: 28 | AL3: 29 | AM3: 30 | AN3: 31 | AO3: 32 | AP3: 33 | AQ3: 34 | AR3: 35 | AS3: 36 | AT3: 37 | AU3: 38 | AV3: 39 | AW3: 40 | AX3: 41 | AY3: 42 | AZ3: 43 | BA3: 44 | BB3: 45 | BC3: 46 | BD3: 47 | BE3: 48 | BF3: 49 | BG3: 50 | BH3: 51 | BI3: 52 | BJ3: 53 | BK3: 54 | BL3: 55 | BM3: 56 | BN3: 57 | BO3: 58 | BP3: 59 | BQ3: 60 | BR3: 61 | BS3: 62 | BT3: 63 | BU3: 64 | BV3: 65 | BW3: 66 | BX3: 67 | BY3: 68 | BZ3: 69 | CA3: 70 | CB3: 71 | CC3: 72 | CD3: 73 | CE3: 74 | CF3: 75 | CG3: 76 | CH3: 77 | CI3: 78 | CJ3: 79 | CK3: 80 | CL3: 81 | CM3: 82 | CN3: 83 | CO3: 84
A4: ACCOUNTS
A5: Businesses Sign Ups
A6: New businesses sign ups | B6: =SUM(J6:U6) -> 33.128191 | C6: =SUM(V6:AG6) -> 70.842263 | D6: =SUM(AH6:AS6) -> 301.09594 | E6: =SUM(AT6:BE6) -> 1762.1401 | F6: =SUM(BF6:BQ6) -> 9427.8903 | G6: =SUM(BR6:CC6) -> 50441.571 | H6: =SUM(CD6:CO6) -> 269875.02 | J6: =' Inputs'!B8 -> 0 | K6: 2 | L6: 5 | M6: 5 | N6: 5 | O6: =N13*' Inputs'!$C$8 -> 1.7 | P6: =O13*' Inputs'!$C$8 -> 1.87 | Q6: =P13*' Inputs'!$C$8 -> 2.057 | R6: =Q13*' Inputs'!$C$8 -> 2.2627 | S6: =R13*' Inputs'!$C$8 -> 2.48897 | T6: =S13*' Inputs'!$C$8 -> 2.737867 | U6: =T13*' Inputs'!$C$8 -> 3.0116537 | V6: =U13*' Inputs'!$D$8 -> 3.3128191 | W6: =V13*' Inputs'!$D$8 -> 3.644101 | X6: =W13*' Inputs'!$D$8 -> 4.0085111 | Y6: =X13*' Inputs'!$D$8 -> 4.4093622 | Z6: =Y13*' Inputs'!$D$8 -> 4.8502984 | AA6: =Z13*' Inputs'!$D$8 -> 5.3353282 | AB6: =AA13*' Inputs'!$D$8 -> 5.8688611 | AC6: =AB13*' Inputs'!$D$8 -> 6.4557472 | ... AG6: =AF13*' Inputs'!$D$8 -> 9.4518594 | AH6: =AG13*' Inputs'!$E$8 -> 12.476454 | AI6: =AH13*' Inputs'!$E$8 -> 13.973629 | AJ6: =AI13*' Inputs'!$E$8 -> 15.650464 | AK6: =AJ13*' Inputs'!$E$8 -> 17.52852 | AL6: =AK13*' Inputs'!$E$8 -> 19.631943 | AM6: =AL13*' Inputs'!$E$8 -> 21.987776 | AN6: =AM13*' Inputs'!$E$8 -> 24.626309 | AO6: =AN13*' Inputs'!$E$8 -> 27.581466 | ... AS6: =AR13*' Inputs'!$E$8 -> 43.399971 | AT6: =AS13*' Inputs'!$F$8 -> 60.759959 | AU6: =AT13*' Inputs'!$F$8 -> 69.873953 | AV6: =AU13*' Inputs'!$F$8 -> 80.355045 | AW6: =AV13*' Inputs'!$F$8 -> 92.408302 | AX6: =AW13*' Inputs'!$F$8 -> 106.26955 | AY6: =AX13*' Inputs'!$F$8 -> 122.20998 | AZ6: =AY13*' Inputs'!$F$8 -> 140.54148 | BA6: =AZ13*' Inputs'!$F$8 -> 161.6227 | ... BE6: =BD13*' Inputs'!$F$8 -> 282.67911 | BF6: =BE13*' Inputs'!$G$8 -> 325.08098 | BG6: =BF13*' Inputs'!$G$8 -> 373.84312 | BH6: =BG13*' Inputs'!$G$8 -> 429.91959 | BI6: =BH13*' Inputs'!$G$8 -> 494.40753 | BJ6: =BI13*' Inputs'!$G$8 -> 568.56866 | BK6: =BJ13*' Inputs'!$G$8 -> 653.85396 | BL6: =BK13*' Inputs'!$G$8 -> 751.93205 | BM6: =BL13*' Inputs'!$G$8 -> 864.72186 | ... BQ6: =BP13*' Inputs'!$G$8 -> 1512.4039 | BR6: =BQ13*' Inputs'!$H$8 -> 1739.2645 | BS6: =BR13*' Inputs'!$H$8 -> 2000.1542 | BT6: =BS13*' Inputs'!$H$8 -> 2300.1773 | BU6: =BT13*' Inputs'!$H$8 -> 2645.2039 | BV6: =BU13*' Inputs'!$H$8 -> 3041.9845 | BW6: =BV13*' Inputs'!$H$8 -> 3498.2822 | BX6: =BW13*' Inputs'!$H$8 -> 4023.0245 | BY6: =BX13*' Inputs'!$H$8 -> 4626.4782 | ... CO6: =CN13*' Inputs'!$H$8 -> 43292.829
A7: % organic sign ups | B7: =' Inputs'!C7 -> 0.05 | C7: =' Inputs'!D7 -> 0.25 | D7: =' Inputs'!E7 -> 0.5 | E7: =' Inputs'!F7 -> 0.5 | F7: =' Inputs'!G7 -> 0.5 | G7: =' Inputs'!H7 -> 0.5 | H7: =' Inputs'!I7 -> 0.5
A8: Organic businesses | B8: =B6*B7 -> 1.6564095 | C8: =C6*C7 -> 17.710566 | D8: =D6*D7 -> 150.54797 | E8: =E6*E7 -> 881.07006 | F8: =F6*F7 -> 4713.9452 | G8: =G6*G7 -> 25220.786 | H8: =H6*H7 -> 134937.51
A9: Paid businesses | B9: =B6-B8 -> 31.471781 | C9: =C6-C8 -> 53.131697 | D9: =D6-D8 -> 150.54797 | E9: =E6-E8 -> 881.07006 | F9: =F6-F8 -> 4713.9452 | G9: =G6-G8 -> 25220.786 | H9: =H6-H8 -> 134937.51
A10: Business acquisition cost (per) | B10: =' Inputs'!C6 -> 50 | C10: =' Inputs'!D6 -> 50 | D10: =' Inputs'!E6 -> 50 | E10: =' Inputs'!F6 -> 50 | F10: =' Inputs'!G6 -> 50 | G10: =' Inputs'!H6 -> 50 | H10: =' Inputs'!I6 -> 50
A11: Total business acqusition cost | B11: =B9*B10 -> 1573.5891 | C11: =C9*C10 -> 2656.5849 | D11: =D9*D10 -> 7527.3985 | E11: =E9*E10 -> 44053.503 | F11: =F9*F10 -> 235697.26 | G11: =G9*G10 -> 1261039.3 | H11: =H9*H10 -> 6746875.5
A12: Business churn | B12: =B6*churn1 -> 1.6564095 | C12: =C6*churn2 -> 3.5421132 | D12: =D6*churn3 -> 15.054797 | E12: =E6*churn4 -> 88.107006 | F12: =F6*churn5 -> 471.39452 | G12: =G6*churn6 -> 2522.0786 | H12: =H6*churn7 -> 13493.751
A13: Total Businesses (ending) | B13: =B6-B12 -> 31.471781 | C13: =B13+C6-C12 -> 98.771931 | D13: =AS13-D12 -> 390.01159 | E13: =BE13-E12 -> 2079.0995 | F13: =BQ13-F12 -> 11123.702 | G13: =CC13-G12 -> 59514.589 | H13: =CO13-H12 -> 318417.94 | J13: 0 | K13: =J13+K6 -> 2 | L13: =K13+L6 -> 7 | M13: =L13+M6 -> 12 | N13: =M13+N6 -> 17 | O13: =N13+O6 -> 18.7 | P13: =O13+P6 -> 20.57 | Q13: =P13+Q6 -> 22.627 | R13: =Q13+R6 -> 24.8897 | ... CO13: =CN13+CO6 -> 331911.69
A15: Users Sign Ups
A16: New users sign ups | B16: =SUM(J16:U16) -> 20000 | C16: =SUM(V16:AG16) -> 57317.82 | D16: =SUM(AH16:AS16) -> 1045831.3 | E16: =SUM(AT16:BE16) -> 4273022.3 | F16: =SUM(BF16:BQ16) -> 7906753 | G16: =SUM(BR16:CC16) -> 10511353 | H16: =SUM(CD16:CO16) -> 13124193 | J16: 500 | K16: 500 | L16: 500 | M16: 500 | N16: 500 | O16: 800 | P16: 1200 | Q16: 2500 | R16: 3000 | S16: 3000 | T16: 3000 | U16: 4000 | V16: =users_y2/12 -> 4776.485 | W16: =users_y2/12 -> 4776.485 | X16: =users_y2/12 -> 4776.485 | Y16: =users_y2/12 -> 4776.485 | Z16: =users_y2/12 -> 4776.485 | AA16: =users_y2/12 -> 4776.485 | AB16: =users_y2/12 -> 4776.485 | AC16: =users_y2/12 -> 4776.485 | ... AG16: =users_y2/12 -> 4776.485 | AH16: =users_y3/12 -> 87152.612 | AI16: =users_y3/12 -> 87152.612 | AJ16: =users_y3/12 -> 87152.612 | AK16: =users_y3/12 -> 87152.612 | AL16: =users_y3/12 -> 87152.612 | AM16: =users_y3/12 -> 87152.612 | AN16: =users_y3/12 -> 87152.612 | AO16: =users_y3/12 -> 87152.612 | ... AS16: =users_y3/12 -> 87152.612 | AT16: =users_y4/12 -> 356085.2 | AU16: =users_y4/12 -> 356085.2 | AV16: =users_y4/12 -> 356085.2 | AW16: =users_y4/12 -> 356085.2 | AX16: =users_y4/12 -> 356085.2 | AY16: =users_y4/12 -> 356085.2 | AZ16: =users_y4/12 -> 356085.2 | BA16: =users_y4/12 -> 356085.2 | ... BE16: =users_y4/12 -> 356085.2 | BF16: =users_y5/12 -> 658896.08 | BG16: =users_y5/12 -> 658896.08 | BH16: =users_y5/12 -> 658896.08 | BI16: =users_y5/12 -> 658896.08 | BJ16: =users_y5/12 -> 658896.08 | BK16: =users_y5/12 -> 658896.08 | BL16: =users_y5/12 -> 658896.08 | BM16: =users_y5/12 -> 658896.08 | ... BQ16: =users_y5/12 -> 658896.08 | BR16: =users_y6/12 -> 875946.08 | BS16: =users_y6/12 -> 875946.08 | BT16: =users_y6/12 -> 875946.08 | BU16: =users_y6/12 -> 875946.08 | BV16: =users_y6/12 -> 875946.08 | BW16: =users_y6/12 -> 875946.08 | BX16: =users_y6/12 -> 875946.08 | BY16: =users_y6/12 -> 875946.08 | ... CC16: =users_y6/12 -> 875946.08 | CD16: =users_y7/12 -> 1093682.8 | CE16: =users_y7/12 -> 1093682.8 | CF16: =users_y7/12 -> 1093682.8 | CG16: =users_y7/12 -> 1093682.8 | CH16: =users_y7/12 -> 1093682.8 | CI16: =users_y7/12 -> 1093682.8 | CJ16: =users_y7/12 -> 1093682.8 | CK16: =users_y7/12 -> 1093682.8 | ... CO16: =users_y7/12 -> 1093682.8
A17: % organic sign ups | B17: 0.5 | C17: =' Inputs'!D14 -> 0.3 | D17: =' Inputs'!E14 -> 0.3 | E17: =' Inputs'!F14 -> 0.4 | F17: =' Inputs'!G14 -> 0.5 | G17: =' Inputs'!H14 -> 0.5 | H17: =' Inputs'!I14 -> 0.5
A18: Organic user sign ups | B18: =B16*B17 -> 10000 | C18: =C16*C17 -> 17195.346 | D18: =D16*D17 -> 313749.4 | E18: =E16*E17 -> 1709208.9 | F18: =F16*F17 -> 3953376.5 | G18: =G16*G17 -> 5255676.5 | H18: =H16*H17 -> 6562096.6
A19: Paid user sign ups | B19: =B16-B18 -> 10000 | C19: =C16-C18 -> 40122.474 | D19: =D16-D18 -> 732081.94 | E19: =E16-E18 -> 2563813.4 | F19: =F16-F18 -> 3953376.5 | G19: =G16-G18 -> 5255676.5 | H19: =H16-H18 -> 6562096.6
A20: Customer user cost (per) | B20: 5 | C20: 5 | D20: 5 | E20: 5 | F20: 5 | G20: 5 | H20: 5
A21: Total user acquistion cost | B21: =B19*B20 -> 50000 | C21: =C19*C20 -> 200612.37 | D21: =D19*D20 -> 3660409.7 | E21: =E19*E20 -> 12819067 | F21: =F19*F20 -> 19766883 | G21: =G19*G20 -> 26278382 | H21: =H19*H20 -> 32810483
A22: User churn | B22: =B16*' Inputs'!C15 -> 1000 | C22: =C16*' Inputs'!D15 -> 2865.891 | D22: =D16*' Inputs'!E15 -> 52291.567 | E22: =E16*' Inputs'!F15 -> 213651.12 | F22: =F16*' Inputs'!G15 -> 395337.65 | G22: =G16*' Inputs'!H15 -> 525567.65 | H22: =H16*' Inputs'!I15 -> 656209.66
A23: Total Users (ending) | B23: =B16-B22 -> 19000 | C23: =B23+C16-C22 -> 73451.929 | D23: =C23+D16-D22 -> 1066991.7 | E23: =D23+E16-E22 -> 5126362.9 | F23: =E23+F16-F22 -> 12637778 | G23: =F23+G16-G22 -> 22623564 | H23: =G23+H16-H22 -> 35091547
A25: REVENUE
A26: User advertising revenue | B26: =SUM(J26:U26) -> #REF! | C26: =SUM(V26:AG26) -> #REF! | D26: =SUM(AH26:AS26) -> #REF! | E26: =SUM(AT26:BE26) -> #REF! | F26: =SUM(BF26:BQ26) -> #REF! | G26: =SUM(BR26:CC26) -> #REF! | H26: =SUM(CD26:CO26) -> #REF! | J26: =#REF!*' Inputs'!$C$33*' Inputs'!$C$34 -> #REF! | K26: =#REF!*' Inputs'!$C$33*' Inputs'!$C$34 -> #REF! | L26: =#REF!*' Inputs'!$C$33*' Inputs'!$C$34 -> #REF! | M26: =#REF!*' Inputs'!$C$33*' Inputs'!$C$34 -> #REF! | N26: =#REF!*' Inputs'!$C$33*' Inputs'!$C$34 -> #REF! | O26: =#REF!*' Inputs'!$C$33*' Inputs'!$C$34 -> #REF! | P26: =#REF!*' Inputs'!$C$33*' Inputs'!$C$34 -> #REF! | Q26: =#REF!*' Inputs'!$C$33*' Inputs'!$C$34 -> #REF! | ... U26: =#REF!*' Inputs'!$C$33*' Inputs'!$C$34 -> #REF! | V26: =#REF!*' Inputs'!$D$33*' Inputs'!$D$34 -> #REF! | W26: =#REF!*' Inputs'!$D$33*' Inputs'!$D$34 -> #REF! | X26: =#REF!*' Inputs'!$D$33*' Inputs'!$D$34 -> #REF! | Y26: =#REF!*' Inputs'!$D$33*' Inputs'!$D$34 -> #REF! | Z26: =#REF!*' Inputs'!$D$33*' Inputs'!$D$34 -> #REF! | AA26: =#REF!*' Inputs'!$D$33*' Inputs'!$D$34 -> #REF! | AB26: =#REF!*' Inputs'!$D$33*' Inputs'!$D$34 -> #REF! | AC26: =#REF!*' Inputs'!$D$33*' Inputs'!$D$34 -> #REF! | ... AG26: =#REF!*' Inputs'!$D$33*' Inputs'!$D$34 -> #REF! | AH26: =#REF!*' Inputs'!$E$33*' Inputs'!$E$34 -> #REF! | AI26: =#REF!*' Inputs'!$E$33*' Inputs'!$E$34 -> #REF! | AJ26: =#REF!*' Inputs'!$E$33*' Inputs'!$E$34 -> #REF! | AK26: =#REF!*' Inputs'!$E$33*' Inputs'!$E$34 -> #REF! | AL26: =#REF!*' Inputs'!$E$33*' Inputs'!$E$34 -> #REF! | AM26: =#REF!*' Inputs'!$E$33*' Inputs'!$E$34 -> #REF! | AN26: =#REF!*' Inputs'!$E$33*' Inputs'!$E$34 -> #REF! | AO26: =#REF!*' Inputs'!$E$33*' Inputs'!$E$34 -> #REF! | ... AS26: =#REF!*' Inputs'!$E$33*' Inputs'!$E$34 -> #REF! | AT26: =#REF!*' Inputs'!$F$33*' Inputs'!$F$34 -> #REF! | AU26: =#REF!*' Inputs'!$F$33*' Inputs'!$F$34 -> #REF! | AV26: =#REF!*' Inputs'!$F$33*' Inputs'!$F$34 -> #REF! | AW26: =#REF!*' Inputs'!$F$33*' Inputs'!$F$34 -> #REF! | AX26: =#REF!*' Inputs'!$F$33*' Inputs'!$F$34 -> #REF! | AY26: =#REF!*' Inputs'!$F$33*' Inputs'!$F$34 -> #REF! | AZ26: =#REF!*' Inputs'!$F$33*' Inputs'!$F$34 -> #REF! | BA26: =#REF!*' Inputs'!$F$33*' Inputs'!$F$34 -> #REF! | ... BE26: =#REF!*' Inputs'!$F$33*' Inputs'!$F$34 -> #REF! | BF26: =#REF!*' Inputs'!$G$33*' Inputs'!$G$34 -> #REF! | BG26: =#REF!*' Inputs'!$G$33*' Inputs'!$G$34 -> #REF! | BH26: =#REF!*' Inputs'!$G$33*' Inputs'!$G$34 -> #REF! | BI26: =#REF!*' Inputs'!$G$33*' Inputs'!$G$34 -> #REF! | BJ26: =#REF!*' Inputs'!$G$33*' Inputs'!$G$34 -> #REF! | BK26: =#REF!*' Inputs'!$G$33*' Inputs'!$G$34 -> #REF! | BL26: =#REF!*' Inputs'!$G$33*' Inputs'!$G$34 -> #REF! | BM26: =#REF!*' Inputs'!$G$33*' Inputs'!$G$34 -> #REF! | ... BQ26: =#REF!*' Inputs'!$G$33*' Inputs'!$G$34 -> #REF! | BR26: =#REF!*' Inputs'!$H$33*' Inputs'!$H$34 -> #REF! | BS26: =#REF!*' Inputs'!$H$33*' Inputs'!$H$34 -> #REF! | BT26: =#REF!*' Inputs'!$H$33*' Inputs'!$H$34 -> #REF! | BU26: =#REF!*' Inputs'!$H$33*' Inputs'!$H$34 -> #REF! | BV26: =#REF!*' Inputs'!$H$33*' Inputs'!$H$34 -> #REF! | BW26: =#REF!*' Inputs'!$H$33*' Inputs'!$H$34 -> #REF! | BX26: =#REF!*' Inputs'!$H$33*' Inputs'!$H$34 -> #REF! | BY26: =#REF!*' Inputs'!$H$33*' Inputs'!$H$34 -> #REF! | ... CO26: =#REF!*' Inputs'!$H$33*' Inputs'!$H$34 -> #REF!
A27: User subscription revenue | B27: =' Inputs'!C32*' Inputs'!C33*Summary!B17 -> 0 | C27: =' Inputs'!D32*' Inputs'!D33*Summary!C17 -> 0 | D27: =' Inputs'!E32*' Inputs'!E33*Summary!D17 -> 0 | E27: =' Inputs'!F32*' Inputs'!F33*Summary!E17 -> 0 | F27: =' Inputs'!G32*' Inputs'!G33*Summary!F17 -> 0 | G27: =' Inputs'!H32*' Inputs'!H33*Summary!G17 -> 0 | H27: =' Inputs'!I32*' Inputs'!I33*Summary!H17 -> 0
A28: Pro advertising revenue
A29: Pro subscription revenue | B29: =SUM(J29:U29) -> 0 | C29: =SUM(V29:AG29) -> 19481.622 | D29: =SUM(AH29:AS29) -> 140511.44 | E29: =SUM(AT29:BE29) -> 1350974.1 | F29: =SUM(BF29:BQ29) -> 7228049.3 | G29: =SUM(BR29:CC29) -> 38671871 | H29: =SUM(CD29:CO29) -> 2.0690418e+08 | J29: =' Inputs'!$C$29*Summary!J13 -> 0 | K29: =' Inputs'!$C$29*Summary!K13 -> 0 | L29: =' Inputs'!$C$29*Summary!L13 -> 0 | M29: =' Inputs'!$C$29*Summary!M13 -> 0 | N29: =' Inputs'!$C$29*Summary!N13 -> 0 | O29: =' Inputs'!$C$29*Summary!O13 -> 0 | P29: =' Inputs'!$C$29*Summary!P13 -> 0 | Q29: =' Inputs'!$C$29*Summary!Q13 -> 0 | ... U29: =' Inputs'!$C$29*Summary!U13 -> 0 | V29: =' Inputs'!$D$29*Summary!V13 -> 911.02524 | W29: =' Inputs'!$D$29*Summary!W13 -> 1002.1278 | X29: =' Inputs'!$D$29*Summary!X13 -> 1102.3405 | Y29: =' Inputs'!$D$29*Summary!Y13 -> 1212.5746 | Z29: =' Inputs'!$D$29*Summary!Z13 -> 1333.8321 | AA29: =' Inputs'!$D$29*Summary!AA13 -> 1467.2153 | AB29: =' Inputs'!$D$29*Summary!AB13 -> 1613.9368 | AC29: =' Inputs'!$D$29*Summary!AC13 -> 1775.3305 | ... AG29: =' Inputs'!$D$29*Summary!AG13 -> 2599.2613 | AH29: =' Inputs'!$E$29*Summary!AH13 -> 5822.3454 | AI29: =' Inputs'!$E$29*Summary!AI13 -> 6521.0269 | AJ29: =' Inputs'!$E$29*Summary!AJ13 -> 7303.5501 | AK29: =' Inputs'!$E$29*Summary!AK13 -> 8179.9761 | AL29: =' Inputs'!$E$29*Summary!AL13 -> 9161.5732 | AM29: =' Inputs'!$E$29*Summary!AM13 -> 10260.962 | AN29: =' Inputs'!$E$29*Summary!AN13 -> 11492.277 | AO29: =' Inputs'!$E$29*Summary!AO13 -> 12871.351 | ... AS29: =' Inputs'!$E$29*Summary!AS13 -> 20253.32 | AT29: =' Inputs'!$F$29*Summary!AT13 -> 46582.635 | AU29: =' Inputs'!$F$29*Summary!AU13 -> 53570.03 | AV29: =' Inputs'!$F$29*Summary!AV13 -> 61605.535 | AW29: =' Inputs'!$F$29*Summary!AW13 -> 70846.365 | AX29: =' Inputs'!$F$29*Summary!AX13 -> 81473.32 | AY29: =' Inputs'!$F$29*Summary!AY13 -> 93694.318 | AZ29: =' Inputs'!$F$29*Summary!AZ13 -> 107748.47 | BA29: =' Inputs'!$F$29*Summary!BA13 -> 123910.74 | ... BE29: =' Inputs'!$F$29*Summary!BE13 -> 216720.65 | BF29: =' Inputs'!$G$29*Summary!BF13 -> 249228.75 | BG29: =' Inputs'!$G$29*Summary!BG13 -> 286613.06 | BH29: =' Inputs'!$G$29*Summary!BH13 -> 329605.02 | BI29: =' Inputs'!$G$29*Summary!BI13 -> 379045.77 | BJ29: =' Inputs'!$G$29*Summary!BJ13 -> 435902.64 | BK29: =' Inputs'!$G$29*Summary!BK13 -> 501288.03 | BL29: =' Inputs'!$G$29*Summary!BL13 -> 576481.24 | BM29: =' Inputs'!$G$29*Summary!BM13 -> 662953.42 | ... BQ29: =' Inputs'!$G$29*Summary!BQ13 -> 1159509.7 | BR29: =' Inputs'!$H$29*Summary!BR13 -> 1333436.1 | BS29: =' Inputs'!$H$29*Summary!BS13 -> 1533451.6 | BT29: =' Inputs'!$H$29*Summary!BT13 -> 1763469.3 | BU29: =' Inputs'!$H$29*Summary!BU13 -> 2027989.7 | BV29: =' Inputs'!$H$29*Summary!BV13 -> 2332188.1 | BW29: =' Inputs'!$H$29*Summary!BW13 -> 2682016.4 | BX29: =' Inputs'!$H$29*Summary!BX13 -> 3084318.8 | BY29: =' Inputs'!$H$29*Summary!BY13 -> 3546966.6 | ... CC29: =' Inputs'!$H$29*Summary!CC13 -> 6203666.8 | CD29: =' Inputs'!$I$29*Summary!CD13 -> 7134216.8 | CE29: =' Inputs'!$I$29*Summary!CE13 -> 8204349.4 | CF29: =' Inputs'!$I$29*Summary!CF13 -> 9435001.8 | CG29: =' Inputs'!$I$29*Summary!CG13 -> 10850252 | CH29: =' Inputs'!$I$29*Summary!CH13 -> 12477790 | CI29: =' Inputs'!$I$29*Summary!CI13 -> 14349458 | CJ29: =' Inputs'!$I$29*Summary!CJ13 -> 16501877 | CK29: =' Inputs'!$I$29*Summary!CK13 -> 18977159 | ... CO29: =' Inputs'!$I$29*Summary!CO13 -> 33191169
A30: Transaction revenue
A31: TOTAL REVENUE | B31: =#REF!+B29+B26+#REF!+#REF! -> #REF! | C31: =#REF!+C29+C26+#REF!+#REF! -> #REF! | D31: =#REF!+D29+D26+#REF!+#REF! -> #REF! | E31: =#REF!+E29+E26+#REF!+#REF! -> #REF! | F31: =#REF!+F29+F26+#REF!+#REF! -> #REF! | G31: =#REF!+G29+G26+#REF!+#REF! -> #REF! | H31: =#REF!+H29+H26+#REF!+#REF! -> #REF! | J31: =SUM(J29:J29) -> 0 | K31: =SUM(K29:K29) -> 0 | L31: =SUM(L29:L29) -> 0 | M31: =SUM(M29:M29) -> 0 | N31: =SUM(N29:N29) -> 0 | O31: =SUM(O29:O29) -> 0 | P31: =SUM(P29:P29) -> 0 | Q31: =SUM(Q29:Q29) -> 0 | ... CO31: =SUM(CO29:CO29) -> 33191169
A33: EXPENSES
A34: Growth Marketing
A35: Business acquisition cost | B35: =B11 -> 1573.5891 | C35: =C11 -> 2656.5849 | D35: =D11 -> 7527.3985 | E35: =E11 -> 44053.503 | F35: =F11 -> 235697.26 | G35: =G11 -> 1261039.3 | H35: =H11 -> 6746875.5
A36: User acquisition cost | B36: =B21 -> 50000 | C36: =C21 -> 200612.37 | D36: =D21 -> 3660409.7 | E36: =E21 -> 12819067 | F36: =F21 -> 19766883 | G36: =G21 -> 26278382 | H36: =H21 -> 32810483
A37: MSA launch cost | B37: =SUMIF(Merchants!$N$4:$N$11, 1, Merchants!$M$4:$M$11) -> 33075.8 | C37: =SUMIF(Merchants!$N$4:$N$11, 2, Merchants!$M$4:$M$11) -> 407799.2 | D37: =SUMIF(Merchants!$N$4:$N$11, 3, Merchants!$M$4:$M$11) -> 105956.5 | E37: =SUMIF(Merchants!$N$4:$N$11, 4, Merchants!$M$4:$M$11) -> 7370252.7 | F37: =SUMIF(Merchants!$N$4:$N$11, 5, Merchants!$M$4:$M$11) -> 10621012 | G37: =SUMIF(Merchants!$N$4:$N$11, 6, Merchants!$M$4:$M$11) -> 10322809 | H37: =SUMIF(Merchants!$N$4:$N$11, 7, Merchants!$M$4:$M$11) -> 0
A38: Operating Expenses | B38: =SUM(J38:U38) -> 673900 | C38: =SUM(V38:AG38) -> 864600 | D38: =SUM(AH38:AS38) -> #REF! | E38: =D38 -> #REF! | F38: =E38 -> #REF! | G38: =F38 -> #REF! | H38: =G38 -> #REF! | J38: ='Expenses Yr1-2'!D34 -> 42158.333 | K38: ='Expenses Yr1-2'!E34 -> 42158.333 | L38: ='Expenses Yr1-2'!F34 -> 42158.333 | M38: ='Expenses Yr1-2'!G34 -> 42158.333 | N38: ='Expenses Yr1-2'!H34 -> 42158.333 | O38: ='Expenses Yr1-2'!I34 -> 66158.333 | P38: ='Expenses Yr1-2'!J34 -> 66158.333 | Q38: ='Expenses Yr1-2'!K34 -> 66158.333 | ... AG38: ='Expenses Yr1-2'!AA34 -> 72258.333 | AH38: ='Expenses Yr1-2'!#REF! -> #REF! | AI38: ='Expenses Yr1-2'!#REF! -> #REF! | AJ38: ='Expenses Yr1-2'!#REF! -> #REF! | AK38: ='Expenses Yr1-2'!#REF! -> #REF! | AL38: ='Expenses Yr1-2'!#REF! -> #REF! | AM38: ='Expenses Yr1-2'!#REF! -> #REF! | AN38: ='Expenses Yr1-2'!#REF! -> #REF! | AO38: ='Expenses Yr1-2'!#REF! -> #REF! | ... AS38: ='Expenses Yr1-2'!#REF! -> #REF!
A39: Variable (% of rev) | B39: 0 | C39: 0 | D39: 0 | E39: =' Inputs'!C60*Summary!E31 -> #REF! | F39: =F31*' Inputs'!C61 -> #REF! | G39: =' Inputs'!C62*Summary!G31 -> #REF! | H39: =' Inputs'!C63*H31 -> #REF!
A41: TOTAL EXPENSES | B41: =SUM(B35:B40) -> 758549.39 | C41: =SUM(C35:C40) -> 1475668.2 | D41: =SUM(D35:D40) -> #REF! | E41: =SUM(E35:E40) -> #REF! | F41: =SUM(F35:F40) -> #REF! | G41: =SUM(G35:G40) -> #REF! | H41: =SUM(H35:H40) -> #REF!
A43: CAPITAL
A44: NET INCOME (+/-) | B44: =B31-B41 -> #REF! | C44: =C31-C41 -> #REF! | D44: =D31-D41 -> #REF! | E44: =E31-E41 -> #REF! | F44: =F31-F41 -> #REF! | G44: =G31-G41 -> #REF! | H44: =H31-H41 -> #REF!
B46: Denver Metro | C46: Colorado | D46: Top 10 MSAs | E46: Top 50 MSAs | F46: Nationwide
A47: CAPITAL IN | B47: 2000000 | C47: 3000000 | D47: 25000000 | E47: 50000000 | F47: 100000000
A48: CASH AT START | B48: 0 | C48: =B49 -> #REF! | D48: =C49 -> #REF! | E48: =D49 -> #REF! | F48: =E49 -> #REF! | G48: =F49 -> #REF! | H48: =G49 -> #REF!
A49: CASH AT END | B49: =B48+B44+B47 -> #REF! | C49: =C48+C44+C47 -> #REF! | D49: =D48+D44+D47 -> #REF! | E49: =E48+E44+E47 -> #REF! | F49: =F48+F44+F47 -> #REF! | G49: =G48+G44+G47 -> #REF! | H49: =H48+H44+H47 -> #REF!
B50: Pre-Seed | C50: Seed | D50: Series A

Sheet Subscription
A1: SaaS Metrics
A2: MRR, ARR
A3: MoM, YoY, CMGR
A4: MRR dynamics- new, churned, expansion, contraction
A5: LTV
A6: CAC & LTV:CAC ratio
A7: Burn/Runway
A8: Financials (MoM & Budget vs Actuals)
A10: Trial/Discount
A11: Refunds
C12: Year 1 | D12: Year 2 | E12: Year 3 | F12: Year 4 | G12: Year 5 | H12: Year 6 | I12: Year 7
A13: Free | B13: 0 | C13: 0.9 | D13: 0.85 | E13: 0.8 | F13: 0.6 | G13: 0.6 | H13: 0.45 | I13: 0.5
A14: Paid Tier 1 | B14: 20 | C14: 0.1 | D14: 0.1 | E14: 0.15 | F14: 0.2 | G14: 0.2 | H14: 0.3 | I14: 0.3
A15: Paid Tier 2 | B15: 50 | C15: 0 | D15: 0.05 | E15: 0.05 | F15: 0.13 | G15: 0.13 | H15: 0.15 | I15: 0.15
A16: Paid Tier 3 | B16: 100 | C16: 0 | D16: 0 | E16: 0.05 | F16: 0.07 | G16: 0.07 | H16: 0.1 | I16: 0.1
A18: Free
A19: Subscribers
A20: Net Add
A21: Churn
A22: Net Total
A24: New
A25: Expansion (upsell)
A26: Churn
A27: Net New
A29: Total Pro Accounts
A30: Avg # of Subscribers
A35: Average Revenue Per Account
... A38: Annual Reoccuring Revenue

Sheet Transactions
B1: 2024 | C1: 2025 | D1: 2026 | E1: 2027 | F1: 2028 | G1: 2029 | H1: 2030 | J1: =' Inputs'!B3 -> 45292 | K1: =J1+31 -> 45323 | L1: =K1+31 -> 45354 | M1: =L1+31 -> 45385 | N1: =M1+31 -> 45416 | O1: =N1+31 -> 45447 | P1: =O1+31 -> 45478 | Q1: =P1+31 -> 45509 | R1: =Q1+31 -> 45540 | ... CO1: =CN1+31 -> 47865
B2: Year 1 | C2: Year 2 | D2: Year 3 | E2: Year 4 | F2: Year 5 | G2: Year 6 | H2: Year 7 | J2: =CONCATENATE("Month ", J3) -> Month 1 | K2: =CONCATENATE("Month ", K3) -> Month 2 | L2: =CONCATENATE("Month ", L3) -> Month 3 | M2: =CONCATENATE("Month ", M3) -> Month 4 | N2: =CONCATENATE("Month ", N3) -> Month 5 | O2: =CONCATENATE("Month ", O3) -> Month 6 | P2: =CONCATENATE("Month ", P3) -> Month 7 | Q2: =CONCATENATE("Month ", Q3) -> Month 8 | ... CO2: =CONCATENATE("Month ", CO3) -> Month 84
J3: 1 | K3: 2 | L3: 3 | M3: 4 | N3: 5 | O3: 6 | P3: 7 | Q3: 8 | R3: 9 | S3: 10 | T3: 11 | U3: 12 | V3: 13 | W3: 14 | X3: 15 | Y3: 16 | Z3: 17 | AA3: 18 | AB3: 19 | AC3: 20 | AD3: 21 | AE3: 22 | AF3: 23 | AG3: 24 | AH3: 25 | AI3: 26 | AJ3: 27 | AK3: 28 | AL3: 29 | AM3: 30 | AN3: 31 | AO3: 32 | AP3: 33 | AQ3: 34 | AR3: 35 | AS3: 36 | AT3: 37 | AU3: 38 | AV3: 39 | AW3: 40 | AX3: 41 | AY3: 42 | AZ3: 43 | BA3: 44 | BB3: 45 | BC3: 46 | BD3: 47 | BE3: 48 | BF3: 49 | BG3: 50 | BH3: 51 | BI3: 52 | BJ3: 53 | BK3: 54 | BL3: 55 | BM3: 56 | BN3: 57 | BO3: 58 | BP3: 59 | BQ3: 60 | BR3: 61 | BS3: 62 | BT3: 63 | BU3: 64 | BV3: 65 | BW3: 66 | BX3: 67 | BY3: 68 | BZ3: 69 | CA3: 70 | CB3: 71 | CC3: 72 | CD3: 73 | CE3: 74 | CF3: 75 | CG3: 76 | CH3: 77 | CI3: 78 | CJ3: 79 | CK3: 80 | CL3: 81 | CM3: 82 | CN3: 83 | CO3: 84
A4: TRANSACTION REVENUE
A5: Ticket Sales
A6: Avg price per ticket | B6: =' Inputs'!K19 -> 0 | C6: =' Inputs'!L19 -> 0 | D6: =' Inputs'!M19 -> 0 | E6: =' Inputs'!N19 -> 0 | F6: =' Inputs'!O19 -> 0 | G6: =' Inputs'!P19 -> 0 | H6: =' Inputs'!Q19 -> 0 | J6: =' Inputs'!$K$19 -> 0 | K6: =' Inputs'!$K$19 -> 0 | L6: =' Inputs'!$K$19 -> 0 | M6: =' Inputs'!$K$19 -> 0 | N6: =' Inputs'!$K$19 -> 0 | O6: =' Inputs'!$K$19 -> 0 | P6: =' Inputs'!$K$19 -> 0 | Q6: =' Inputs'!$K$19 -> 0 | ... U6: =' Inputs'!$K$19 -> 0 | V6: =' Inputs'!$L$19 -> 0 | W6: =' Inputs'!$L$19 -> 0 | X6: =' Inputs'!$L$19 -> 0 | Y6: =' Inputs'!$L$19 -> 0 | Z6: =' Inputs'!$L$19 -> 0 | AA6: =' Inputs'!$L$19 -> 0 | AB6: =' Inputs'!$L$19 -> 0 | AC6: =' Inputs'!$L$19 -> 0 | ... AG6: =' Inputs'!$L$19 -> 0 | AH6: =' Inputs'!$M$19 -> 0 | AI6: =' Inputs'!$M$19 -> 0 | AJ6: =' Inputs'!$M$19 -> 0 | AK6: =' Inputs'!$M$19 -> 0 | AL6: =' Inputs'!$M$19 -> 0 | AM6: =' Inputs'!$M$19 -> 0 | AN6: =' Inputs'!$M$19 -> 0 | AO6: =' Inputs'!$M$19 -> 0 | ... AS6: =' Inputs'!$M$19 -> 0 | AT6: =' Inputs'!$N$19 -> 0 | AU6: =' Inputs'!$N$19 -> 0 | AV6: =' Inputs'!$N$19 -> 0 | AW6: =' Inputs'!$N$19 -> 0 | AX6: =' Inputs'!$N$19 -> 0 | AY6: =' Inputs'!$N$19 -> 0 | AZ6: =' Inputs'!$N$19 -> 0 | BA6: =' Inputs'!$N$19 -> 0 | ... BE6: =' Inputs'!$N$19 -> 0 | BF6: =' Inputs'!$O$19 -> 0 | BG6: =' Inputs'!$O$19 -> 0 | BH6: =' Inputs'!$O$19 -> 0 | BI6: =' Inputs'!$O$19 -> 0 | BJ6: =' Inputs'!$O$19 -> 0 | BK6: =' Inputs'!$O$19 -> 0 | BL6: =' Inputs'!$O$19 -> 0 | BM6: =' Inputs'!$O$19 -> 0 | ... CO6: =' Inputs'!$O$19 -> 0
A7: Tickets Sold | B7: =SUM(J7:U7) -> #REF! | C7: =SUM(V7:AG7) -> #REF! | D7: =SUM(AH7:AS7) -> #REF! | E7: =SUM(AT7:BE7) -> #REF! | F7: =SUM(BF7:BQ7) -> #REF! | G7: =SUM(BR7:CC7) -> #REF! | H7: =SUM(CD7:CO7) -> #REF! | J7: =#REF!*' Inputs'!#REF! -> #REF! | K7: =#REF!*' Inputs'!#REF! -> #REF! | L7: =#REF!*' Inputs'!#REF! -> #REF! | M7: =#REF!*' Inputs'!#REF! -> #REF! | N7: =#REF!*' Inputs'!#REF! -> #REF! | O7: =#REF!*' Inputs'!#REF! -> #REF! | P7: =#REF!*' Inputs'!#REF! -> #REF! | Q7: =#REF!*' Inputs'!#REF! -> #REF! | ... CO7: =#REF!*' Inputs'!#REF! -> #REF!
A8: Total Ticket Sales | B8: =SUM(J8:U8) -> #REF! | C8: =SUM(V8:AG8) -> #REF! | D8: =SUM(AH8:AS8) -> #REF! | E8: =SUM(AT8:BE8) -> #REF! | F8: =SUM(BF8:BQ8) -> #REF! | G8: =SUM(BR8:CC8) -> #REF! | H8: =SUM(CD8:CO8) -> #REF! | J8: =J7*J6 -> #REF! | K8: =K7*K6 -> #REF! | L8: =L7*L6 -> #REF! | M8: =M7*M6 -> #REF! | N8: =N7*N6 -> #REF! | O8: =O7*O6 -> #REF! | P8: =P7*P6 -> #REF! | Q8: =Q7*Q6 -> #REF! | ... CO8: =CO7*CO6 -> #REF!
A9: Net ticket fee (-Stripe) | B9: =SUM(J9:U9) -> #REF! | C9: =SUM(V9:AG9) -> #REF! | D9: =SUM(AH9:AS9) -> #REF! | E9: =SUM(AT9:BE9) -> #REF! | F9: =SUM(BF9:BQ9) -> #REF! | G9: =SUM(BR9:CC9) -> #REF! | H9: =SUM(CD9:CO9) -> #REF! | J9: =J7*' Inputs'!$C$22 -> #REF! | K9: =K7*' Inputs'!$C$22 -> #REF! | L9: =L7*' Inputs'!$C$22 -> #REF! | M9: =M7*' Inputs'!$C$22 -> #REF! | N9: =N7*' Inputs'!$C$22 -> #REF! | O9: =O7*' Inputs'!$C$22 -> #REF! | P9: =P7*' Inputs'!$C$22 -> #REF! | Q9: =Q7*' Inputs'!$C$22 -> #REF! | ... U9: =U7*' Inputs'!$C$22 -> #REF! | V9: =V7*' Inputs'!$D$22 -> #REF! | W9: =W7*' Inputs'!$D$22 -> #REF! | X9: =X7*' Inputs'!$D$22 -> #REF! | Y9: =Y7*' Inputs'!$D$22 -> #REF! | Z9: =Z7*' Inputs'!$D$22 -> #REF! | AA9: =AA7*' Inputs'!$D$22 -> #REF! | AB9: =AB7*' Inputs'!$D$22 -> #REF! | AC9: =AC7*' Inputs'!$D$22 -> #REF! | ... AG9: =AG7*' Inputs'!$D$22 -> #REF! | AH9: =AH7*' Inputs'!$E$22 -> #REF! | AI9: =AI7*' Inputs'!$E$22 -> #REF! | AJ9: =AJ7*' Inputs'!$E$22 -> #REF! | AK9: =AK7*' Inputs'!$E$22 -> #REF! | AL9: =AL7*' Inputs'!$E$22 -> #REF! | AM9: =AM7*' Inputs'!$E$22 -> #REF! | AN9: =AN7*' Inputs'!$E$22 -> #REF! | AO9: =AO7*' Inputs'!$E$22 -> #REF! | ... AS9: =AS7*' Inputs'!$E$22 -> #REF! | AT9: =AT7*' Inputs'!$F$22 -> #REF! | AU9: =AU7*' Inputs'!$F$22 -> #REF! | AV9: =AV7*' Inputs'!$F$22 -> #REF! | AW9: =AW7*' Inputs'!$F$22 -> #REF! | AX9: =AX7*' Inputs'!$F$22 -> #REF! | AY9: =AY7*' Inputs'!$F$22 -> #REF! | AZ9: =AZ7*' Inputs'!$F$22 -> #REF! | BA9: =BA7*' Inputs'!$F$22 -> #REF! | ... BE9: =BE7*' Inputs'!$F$22 -> #REF! | BF9: =BF7*' Inputs'!$G$22 -> #REF! | BG9: =BG7*' Inputs'!$G$22 -> #REF! | BH9: =BH7*' Inputs'!$G$22 -> #REF! | BI9: =BI7*' Inputs'!$G$22 -> #REF! | BJ9: =BJ7*' Inputs'!$G$22 -> #REF! | BK9: =BK7*' Inputs'!$G$22 -> #REF! | BL9: =BL7*' Inputs'!$G$22 -> #REF! | BM9: =BM7*' Inputs'!$G$22 -> #REF! | ... BQ9: =BQ7*' Inputs'!$G$22 -> #REF! | BR9: =BR7*' Inputs'!$H$22 -> #REF! | BS9: =BS7*' Inputs'!$H$22 -> #REF! | BT9: =BT7*' Inputs'!$H$22 -> #REF! | BU9: =BU7*' Inputs'!$H$22 -> #REF! | BV9: =BV7*' Inputs'!$H$22 -> #REF! | BW9: =BW7*' Inputs'!$H$22 -> #REF! | BX9: =BX7*' Inputs'!$H$22 -> #REF! | BY9: =BY7*' Inputs'!$H$22 -> #REF! | ... CO9: =CO7*' Inputs'!$H$22 -> #REF!
A10: Net transaction fee (-Stripe) | B10: =SUM(J10:U10) -> #REF! | C10: =SUM(V10:AG10) -> #REF! | D10: =SUM(AH10:AS10) -> #REF! | E10: =SUM(AT10:BE10) -> #REF! | F10: =SUM(BF10:BQ10) -> #REF! | G10: =SUM(BR10:CC10) -> #REF! | H10: =SUM(CD10:CO10) -> #REF! | J10: =J8*' Inputs'!$C$26 -> #REF! | K10: =K8*' Inputs'!$C$26 -> #REF! | L10: =L8*' Inputs'!$C$26 -> #REF! | M10: =M8*' Inputs'!$C$26 -> #REF! | N10: =N8*' Inputs'!$C$26 -> #REF! | O10: =O8*' Inputs'!$C$26 -> #REF! | P10: =P8*' Inputs'!$C$26 -> #REF! | Q10: =Q8*' Inputs'!$C$26 -> #REF! | ... U10: =U8*' Inputs'!$C$26 -> #REF! | V10: =V8*' Inputs'!$D$26 -> #REF! | W10: =W8*' Inputs'!$D$26 -> #REF! | X10: =X8*' Inputs'!$D$26 -> #REF! | Y10: =Y8*' Inputs'!$D$26 -> #REF! | Z10: =Z8*' Inputs'!$D$26 -> #REF! | AA10: =AA8*' Inputs'!$D$26 -> #REF! | AB10: =AB8*' Inputs'!$D$26 -> #REF! | AC10: =AC8*' Inputs'!$D$26 -> #REF! | ... AG10: =AG8*' Inputs'!$D$26 -> #REF! | AH10: =AH8*' Inputs'!$E$26 -> #REF! | AI10: =AI8*' Inputs'!$E$26 -> #REF! | AJ10: =AJ8*' Inputs'!$E$26 -> #REF! | AK10: =AK8*' Inputs'!$E$26 -> #REF! | AL10: =AL8*' Inputs'!$E$26 -> #REF! | AM10: =AM8*' Inputs'!$E$26 -> #REF! | AN10: =AN8*' Inputs'!$E$26 -> #REF! | AO10: =AO8*' Inputs'!$E$26 -> #REF! | ... AS10: =AS8*' Inputs'!$E$26 -> #REF! | AT10: =AT8*' Inputs'!$F$26 -> #REF! | AU10: =AU8*' Inputs'!$F$26 -> #REF! | AV10: =AV8*' Inputs'!$F$26 -> #REF! | AW10: =AW8*' Inputs'!$F$26 -> #REF! | AX10: =AX8*' Inputs'!$F$26 -> #REF! | AY10: =AY8*' Inputs'!$F$26 -> #REF! | AZ10: =AZ8*' Inputs'!$F$26 -> #REF! | BA10: =BA8*' Inputs'!$F$26 -> #REF! | ... BE10: =BE8*' Inputs'!$F$26 -> #REF! | BF10: =BF8*' Inputs'!$G$26 -> #REF! | BG10: =BG8*' Inputs'!$G$26 -> #REF! | BH10: =BH8*' Inputs'!$G$26 -> #REF! | BI10: =BI8*' Inputs'!$G$26 -> #REF! | BJ10: =BJ8*' Inputs'!$G$26 -> #REF! | BK10: =BK8*' Inputs'!$G$26 -> #REF! | BL10: =BL8*' Inputs'!$G$26 -> #REF! | BM10: =BM8*' Inputs'!$G$26 -> #REF! | ... BQ10: =BQ8*' Inputs'!$G$26 -> #REF! | BR10: =BR8*' Inputs'!$H$26 -> #REF! | BS10: =BS8*' Inputs'!$H$26 -> #REF! | BT10: =BT8*' Inputs'!$H$26 -> #REF! | BU10: =BU8*' Inputs'!$H$26 -> #REF! | BV10: =BV8*' Inputs'!$H$26 -> #REF! | BW10: =BW8*' Inputs'!$H$26 -> #REF! | BX10: =BX8*' Inputs'!$H$26 -> #REF! | BY10: =BY8*' Inputs'!$H$26 -> #REF! | ... CO10: =CO8*' Inputs'!$H$26 -> #REF!
A11: Nigh ticket revenue | B11: =SUM(J11:U11) -> #REF! | C11: =SUM(V11:AG11) -> #REF! | D11: =SUM(AH11:AS11) -> #REF! | E11: =SUM(AT11:BE11) -> #REF! | F11: =SUM(BF11:BQ11) -> #REF! | G11: =SUM(BR11:CC11) -> #REF! | H11: =SUM(CD11:CO11) -> #REF! | J11: =J9+J10 -> #REF! | K11: =K9+K10 -> #REF! | L11: =L9+L10 -> #REF! | M11: =M9+M10 -> #REF! | N11: =N9+N10 -> #REF! | O11: =O9+O10 -> #REF! | P11: =P9+P10 -> #REF! | Q11: =Q9+Q10 -> #REF! | ... CO11: =CO9+CO10 -> #REF!
A12: Nigh take rate | B12: =B11/B8 -> #REF! | C12: =C11/C8 -> #REF! | D12: =D11/D8 -> #REF! | E12: =E11/E8 -> #REF! | F12: =F11/F8 -> #REF! | G12: =G11/G8 -> #REF! | H12: =H11/H8 -> #REF!
A15: TOTAL REVENUE | B15: =B11+#REF!+#REF!+#REF!+#REF! -> #REF! | C15: =C11+#REF!+#REF!+#REF!+#REF! -> #REF! | D15: =D11+#REF!+#REF!+#REF!+#REF! -> #REF! | E15: =E11+#REF!+#REF!+#REF!+#REF! -> #REF! | F15: =F11+#REF!+#REF!+#REF!+#REF! -> #REF! | G15: =G11+#REF!+#REF!+#REF!+#REF! -> #REF! | H15: =H11+#REF!+#REF!+#REF!+#REF! -> #REF! | J15: =SUM(J11:J13) -> #REF! | K15: =SUM(K11:K13) -> #REF! | L15: =SUM(L11:L13) -> #REF! | M15: =SUM(M11:M13) -> #REF! | N15: =SUM(N11:N13) -> #REF! | O15: =SUM(O11:O13) -> #REF! | P15: =SUM(P11:P13) -> #REF! | Q15: =SUM(Q11:Q13) -> #REF! | ... CO15: =SUM(CO11:CO13) -> #REF!
A17: Avg Total Sales per Business | B17: =B8/#REF! -> #REF! | C17: =C8/#REF! -> #REF! | D17: =D8/#REF! -> #REF! | E17: =E8/#REF! -> #REF! | F17: =F8/#REF! -> #REF! | G17: =G8/#REF! -> #REF! | H17: =H8/#REF! -> #REF! | J17: =J8/#REF! -> #REF! | K17: =K8/#REF! -> #REF! | L17: =L8/#REF! -> #REF! | M17: =M8/#REF! -> #REF! | N17: =N8/#REF! -> #REF! | O17: =O8/#REF! -> #REF! | P17: =P8/#REF! -> #REF! | Q17: =Q8/#REF! -> #REF! | ... CO17: =CO8/#REF! -> #REF!
A18: Nigh Total Revenue per Business | B18: =B15/#REF! -> #REF! | C18: =C15/#REF! -> #REF! | D18: =D15/#REF! -> #REF! | E18: =E15/#REF! -> #REF! | F18: =F15/#REF! -> #REF! | G18: =G15/#REF! -> #REF! | H18: =H15/#REF! -> #REF! | J18: =J15/#REF! -> #REF! | K18: =K15/#REF! -> #REF! | L18: =L15/#REF! -> #REF! | M18: =M15/#REF! -> #REF! | N18: =N15/#REF! -> #REF! | O18: =O15/#REF! -> #REF! | P18: =P15/#REF! -> #REF! | Q18: =Q15/#REF! -> #REF! | ... CO18: =CO15/#REF! -> #REF!
A19: Nigh Revenue % of Biz Sales | B19: =B18/B17 -> #REF! | C19: =C18/C17 -> #REF! | D19: =D18/D17 -> #REF! | E19: =E18/E17 -> #REF! | F19: =F18/F17 -> #REF! | G19: =G18/G17 -> #REF! | H19: =H18/H17 -> #REF! | J19: =J18/J17 -> #REF! | K19: =K18/K17 -> #REF! | L19: =L18/L17 -> #REF! | M19: =M18/M17 -> #REF! | N19: =N18/N17 -> #REF! | O19: =O18/O17 -> #REF! | P19: =P18/P17 -> #REF! | Q19: =Q18/Q17 -> #REF! | ... CO19: =CO18/CO17 -> #REF!

Sheet Subscriptions
B1: 2024 | C1: 2025 | D1: 2026 | E1: 2027 | F1: 2028 | G1: 2029 | H1: 2030 | J1: =' Inputs'!B3 -> 45292 | K1: =J1+31 -> 45323 | L1: =K1+31 -> 45354 | M1: =L1+31 -> 45385 | N1: =M1+31 -> 45416 | O1: =N1+31 -> 45447 | P1: =O1+31 -> 45478 | Q1: =P1+31 -> 45509 | R1: =Q1+31 -> 45540 | ... CO1: =CN1+31 -> 47865
B2: Year 1 | C2: Year 2 | D2: Year 3 | E2: Year 4 | F2: Year 5 | G2: Year 6 | H2: Year 7 | J2: =CONCATENATE("Month ", J3) -> Month 1 | K2: =CONCATENATE("Month ", K3) -> Month 2 | L2: =CONCATENATE("Month ", L3) -> Month 3 | M2: =CONCATENATE("Month ", M3) -> Month 4 | N2: =CONCATENATE("Month ", N3) -> Month 5 | O2: =CONCATENATE("Month ", O3) -> Month 6 | P2: =CONCATENATE("Month ", P3) -> Month 7 | Q2: =CONCATENATE("Month ", Q3) -> Month 8 | ... CO2: =CONCATENATE("Month ", CO3) -> Month 84
J3: 1 | K3: 2 | L3: 3 | M3: 4 | N3: 5 | O3: 6 | P3: 7 | Q3: 8 | R3: 9 | S3: 10 | T3: 11 | U3: 12 | V3: 13 | W3: 14 | X3: 15 | Y3: 16 | Z3: 17 | AA3: 18 | AB3: 19 | AC3: 20 | AD3: 21 | AE3: 22 | AF3: 23 | AG3: 24 | AH3: 25 | AI3: 26 | AJ3: 27 | AK3: 28 | AL3: 29 | AM3: 30 | AN3: 31 | AO3: 32 | AP3: 33 | AQ3: 34 | AR3: 35 | AS3: 36 | AT3: 37 | AU3: 38 | AV3: 39 | AW3: 40 | AX3: 41 | AY3: 42 | AZ3: 43 | BA3: 44 | BB3: 45 | BC3: 46 | BD3: 47 | BE3: 48 | BF3: 49 | BG3: 50 | BH3: 51 | BI3: 52 | BJ3: 53 | BK3: 54 | BL3: 55 | BM3: 56 | BN3: 57 | BO3: 58 | BP3: 59 | BQ3: 60 | BR3: 61 | BS3: 62 | BT3: 63 | BU3: 64 | BV3: 65 | BW3: 66 | BX3: 67 | BY3: 68 | BZ3: 69 | CA3: 70 | CB3: 71 | CC3: 72 | CD3: 73 | CE3: 74 | CF3: 75 | CG3: 76 | CH3: 77 | CI3: 78 | CJ3: 79 | CK3: 80 | CL3: 81 | CM3: 82 | CN3: 83 | CO3: 84
A4: SIGNUPS
A5: Businesses Sign Ups
A6: New businesses sign ups | B6: =SUM(J6:U6) -> 33.128191 | C6: =SUM(V6:AG6) -> 70.842263 | D6: =SUM(AH6:AS6) -> 301.09594 | E6: =SUM(AT6:BE6) -> 1762.1401 | F6: =SUM(BF6:BQ6) -> 9427.8903 | G6: =SUM(BR6:CC6) -> 50441.571 | H6: =SUM(CD6:CO6) -> 269875.02 | J6: =' Inputs'!B8 -> 0 | K6: 2 | L6: 5 | M6: 5 | N6: 5 | O6: =N13*' Inputs'!$C$8 -> 1.7 | P6: =O13*' Inputs'!$C$8 -> 1.87 | Q6: =P13*' Inputs'!$C$8 -> 2.057 | R6: =Q13*' Inputs'!$C$8 -> 2.2627 | S6: =R13*' Inputs'!$C$8 -> 2.48897 | T6: =S13*' Inputs'!$C$8 -> 2.737867 | U6: =T13*' Inputs'!$C$8 -> 3.0116537 | V6: =U13*' Inputs'!$D$8 -> 3.3128191 | W6: =V13*' Inputs'!$D$8 -> 3.644101 | X6: =W13*' Inputs'!$D$8 -> 4.0085111 | Y6: =X13*' Inputs'!$D$8 -> 4.4093622 | Z6: =Y13*' Inputs'!$D$8 -> 4.8502984 | AA6: =Z13*' Inputs'!$D$8 -> 5.3353282 | AB6: =AA13*' Inputs'!$D$8 -> 5.8688611 | AC6: =AB13*' Inputs'!$D$8 -> 6.4557472 | ... AG6: =AF13*' Inputs'!$D$8 -> 9.4518594 | AH6: =AG13*' Inputs'!$E$8 -> 12.476454 | AI6: =AH13*' Inputs'!$E$8 -> 13.973629 | AJ6: =AI13*' Inputs'!$E$8 -> 15.650464 | AK6: =AJ13*' Inputs'!$E$8 -> 17.52852 | AL6: =AK13*' Inputs'!$E$8 -> 19.631943 | AM6: =AL13*' Inputs'!$E$8 -> 21.987776 | AN6: =AM13*' Inputs'!$E$8 -> 24.626309 | AO6: =AN13*' Inputs'!$E$8 -> 27.581466 | ... AS6: =AR13*' Inputs'!$E$8 -> 43.399971 | AT6: =AS13*' Inputs'!$F$8 -> 60.759959 | AU6: =AT13*' Inputs'!$F$8 -> 69.873953 | AV6: =AU13*' Inputs'!$F$8 -> 80.355045 | AW6: =AV13*' Inputs'!$F$8 -> 92.408302 | AX6: =AW13*' Inputs'!$F$8 -> 106.26955 | AY6: =AX13*' Inputs'!$F$8 -> 122.20998 | AZ6: =AY13*' Inputs'!$F$8 -> 140.54148 | BA6: =AZ13*' Inputs'!$F$8 -> 161.6227 | ... BE6: =BD13*' Inputs'!$F$8 -> 282.67911 | BF6: =BE13*' Inputs'!$G$8 -> 325.08098 | BG6: =BF13*' Inputs'!$G$8 -> 373.84312 | BH6: =BG13*' Inputs'!$G$8 -> 429.91959 | BI6: =BH13*' Inputs'!$G$8 -> 494.40753 | BJ6: =BI13*' Inputs'!$G$8 -> 568.56866 | BK6: =BJ13*' Inputs'!$G$8 -> 653.85396 | BL6: =BK13*' Inputs'!$G$8 -> 751.93205 | BM6: =BL13*' Inputs'!$G$8 -> 864.72186 | ... BQ6: =BP13*' Inputs'!$G$8 -> 1512.4039 | BR6: =BQ13*' Inputs'!$H$8 -> 1739.2645 | BS6: =BR13*' Inputs'!$H$8 -> 2000.1542 | BT6: =BS13*' Inputs'!$H$8 -> 2300.1773 | BU6: =BT13*' Inputs'!$H$8 -> 2645.2039 | BV6: =BU13*' Inputs'!$H$8 -> 3041.9845 | BW6: =BV13*' Inputs'!$H$8 -> 3498.2822 | BX6: =BW13*' Inputs'!$H$8 -> 4023.0245 | BY6: =BX13*' Inputs'!$H$8 -> 4626.4782 | ... CO6: =CN13*' Inputs'!$H$8 -> 43292.829
A7: % organic sign ups | B7: =' Inputs'!C7 -> 0.05 | C7: =' Inputs'!D7 -> 0.25 | D7: =' Inputs'!E7 -> 0.5 | E7: =' Inputs'!F7 -> 0.5 | F7: =' Inputs'!G7 -> 0.5 | G7: =' Inputs'!H7 -> 0.5 | H7: =' Inputs'!I7 -> 0.5
A8: Organic businesses | B8: =B6*B7 -> 1.6564095 | C8: =C6*C7 -> 17.710566 | D8: =D6*D7 -> 150.54797 | E8: =E6*E7 -> 881.07006 | F8: =F6*F7 -> 4713.9452 | G8: =G6*G7 -> 25220.786 | H8: =H6*H7 -> 134937.51
A9: Paid businesses | B9: =B6-B8 -> 31.471781 | C9: =C6-C8 -> 53.131697 | D9: =D6-D8 -> 150.54797 | E9: =E6-E8 -> 881.07006 | F9: =F6-F8 -> 4713.9452 | G9: =G6-G8 -> 25220.786 | H9: =H6-H8 -> 134937.51
A10: Business acquisition cost (per) | B10: =' Inputs'!C6 -> 50 | C10: =' Inputs'!D6 -> 50 | D10: =' Inputs'!E6 -> 50 | E10: =' Inputs'!F6 -> 50 | F10: =' Inputs'!G6 -> 50 | G10: =' Inputs'!H6 -> 50 | H10: =' Inputs'!I6 -> 50
A11: Total business acqusition cost | B11: =B9*B10 -> 1573.5891 | C11: =C9*C10 -> 2656.5849 | D11: =D9*D10 -> 7527.3985 | E11: =E9*E10 -> 44053.503 | F11: =F9*F10 -> 235697.26 | G11: =G9*G10 -> 1261039.3 | H11: =H9*H10 -> 6746875.5
A12: Business churn | B12: =B6*churn1 -> 1.6564095 | C12: =C6*churn2 -> 3.5421132 | D12: =D6*churn3 -> 15.054797 | E12: =E6*churn4 -> 88.107006 | F12: =F6*churn5 -> 471.39452 | G12: =G6*churn6 -> 2522.0786 | H12: =H6*churn7 -> 13493.751
A13: Total Businesses (ending) | B13: =B6-B12 -> 31.471781 | C13: =B13+C6-C12 -> 98.771931 | D13: =AS13-D12 -> 390.01159 | E13: =BE13-E12 -> 2079.0995 | F13: =BQ13-F12 -> 11123.702 | G13: =CC13-G12 -> 59514.589 | H13: =CO13-H12 -> 318417.94 | J13: 0 | K13: =J13+K6 -> 2 | L13: =K13+L6 -> 7 | M13: =L13+M6 -> 12 | N13: =M13+N6 -> 17 | O13: =N13+O6 -> 18.7 | P13: =O13+P6 -> 20.57 | Q13: =P13+Q6 -> 22.627 | R13: =Q13+R6 -> 24.8897 | ... CO13: =CN13+CO6 -> 331911.69
A15: Users Sign Ups
A16: New users sign ups | B16: =SUM(J16:U16) -> 20000 | C16: =SUM(V16:AG16) -> 57317.82 | D16: =SUM(AH16:AS16) -> 1045831.3 | E16: =SUM(AT16:BE16) -> 4273022.3 | F16: =SUM(BF16:BQ16) -> 7906753 | G16: =SUM(BR16:CC16) -> 10511353 | H16: =SUM(CD16:CO16) -> 13124193 | J16: 500 | K16: 500 | L16: 500 | M16: 500 | N16: 500 | O16: 800 | P16: 1200 | Q16: 2500 | R16: 3000 | S16: 3000 | T16: 3000 | U16: 4000 | V16: =users_y2/12 -> 4776.485 | W16: =users_y2/12 -> 4776.485 | X16: =users_y2/12 -> 4776.485 | Y16: =users_y2/12 -> 4776.485 | Z16: =users_y2/12 -> 4776.485 | AA16: =users_y2/12 -> 4776.485 | AB16: =users_y2/12 -> 4776.485 | AC16: =users_y2/12 -> 4776.485 | ... AG16: =users_y2/12 -> 4776.485 | AH16: =users_y3/12 -> 87152.612 | AI16: =users_y3/12 -> 87152.612 | AJ16: =users_y3/12 -> 87152.612 | AK16: =users_y3/12 -> 87152.612 | AL16: =users_y3/12 -> 87152.612 | AM16: =users_y3/12 -> 87152.612 | AN16: =users_y3/12 -> 87152.612 | AO16: =users_y3/12 -> 87152.612 | ... AS16: =users_y3/12 -> 87152.612 | AT16: =users_y4/12 -> 356085.2 | AU16: =users_y4/12 -> 356085.2 | AV16: =users_y4/12 -> 356085.2 | AW16: =users_y4/12 -> 356085.2 | AX16: =users_y4/12 -> 356085.2 | AY16: =users_y4/12 -> 356085.2 | AZ16: =users_y4/12 -> 356085.2 | BA16: =users_y4/12 -> 356085.2 | ... BE16: =users_y4/12 -> 356085.2 | BF16: =users_y5/12 -> 658896.08 | BG16: =users_y5/12 -> 658896.08 | BH16: =users_y5/12 -> 658896.08 | BI16: =users_y5/12 -> 658896.08 | BJ16: =users_y5/12 -> 658896.08 | BK16: =users_y5/12 -> 658896.08 | BL16: =users_y5/12 -> 658896.08 | BM16: =users_y5/12 -> 658896.08 | ... BQ16: =users_y5/12 -> 658896.08 | BR16: =users_y6/12 -> 875946.08 | BS16: =users_y6/12 -> 875946.08 | BT16: =users_y6/12 -> 875946.08 | BU16: =users_y6/12 -> 875946.08 | BV16: =users_y6/12 -> 875946.08 | BW16: =users_y6/12 -> 875946.08 | BX16: =users_y6/12 -> 875946.08 | BY16: =users_y6/12 -> 875946.08 | ... CC16: =users_y6/12 -> 875946.08 | CD16: =users_y7/12 -> 1093682.8 | CE16: =users_y7/12 -> 1093682.8 | CF16: =users_y7/12 -> 1093682.8 | CG16: =users_y7/12 -> 1093682.8 | CH16: =users_y7/12 -> 1093682.8 | CI16: =users_y7/12 -> 1093682.8 | CJ16: =users_y7/12 -> 1093682.8 | CK16: =users_y7/12 -> 1093682.8 | ... CO16: =users_y7/12 -> 1093682.8
A17: % organic sign ups | B17: =' Inputs'!C14 -> 0.2 | C17: =' Inputs'!D14 -> 0.3 | D17: =' Inputs'!E14 -> 0.3 | E17: =' Inputs'!F14 -> 0.4 | F17: =' Inputs'!G14 -> 0.5 | G17: =' Inputs'!H14 -> 0.5 | H17: =' Inputs'!I14 -> 0.5
A18: Organic user sign ups | B18: =B16*B17 -> 4000 | C18: =C16*C17 -> 17195.346 | D18: =D16*D17 -> 313749.4 | E18: =E16*E17 -> 1709208.9 | F18: =F16*F17 -> 3953376.5 | G18: =G16*G17 -> 5255676.5 | H18: =H16*H17 -> 6562096.6
A19: Paid user sign ups | B19: =B16-B18 -> 16000 | C19: =C16-C18 -> 40122.474 | D19: =D16-D18 -> 732081.94 | E19: =E16-E18 -> 2563813.4 | F19: =F16-F18 -> 3953376.5 | G19: =G16-G18 -> 5255676.5 | H19: =H16-H18 -> 6562096.6
A20: Customer user cost (per) | B20: =' Inputs'!C13 -> 20 | C20: =' Inputs'!D13 -> 15 | D20: =' Inputs'!E13 -> 10 | E20: =' Inputs'!F13 -> 10 | F20: =' Inputs'!G13 -> 10 | G20: =' Inputs'!H13 -> 10 | H20: =' Inputs'!I13 -> 10
A21: Total user acquistion cost | B21: =B19*B20 -> 320000 | C21: =C19*C20 -> 601837.11 | D21: =D19*D20 -> 7320819.4 | E21: =E19*E20 -> 25638134 | F21: =F19*F20 -> 39533765 | G21: =G19*G20 -> 52556765 | H21: =H19*H20 -> 65620966
A22: User churn | B22: =B16*' Inputs'!C15 -> 1000 | C22: =C16*' Inputs'!D15 -> 2865.891 | D22: =D16*' Inputs'!E15 -> 52291.567 | E22: =E16*' Inputs'!F15 -> 213651.12 | F22: =F16*' Inputs'!G15 -> 395337.65 | G22: =G16*' Inputs'!H15 -> 525567.65 | H22: =H16*' Inputs'!I15 -> 656209.66
A23: Total Users (ending) | B23: =B16-B22 -> 19000 | C23: =B23+C16-C22 -> 73451.929 | D23: =C23+D16-D22 -> 1066991.7 | E23: =D23+E16-E22 -> 5126362.9 | F23: =E23+F16-F22 -> 12637778 | G23: =F23+G16-G22 -> 22623564 | H23: =G23+H16-H22 -> 35091547
A25: SALES/REVENUE
A26: Ticket Sales
A27: Avg price per ticket | B27: =' Inputs'!K19 -> 0 | C27: =' Inputs'!L19 -> 0 | D27: =' Inputs'!M19 -> 0 | E27: =' Inputs'!N19 -> 0 | F27: =' Inputs'!O19 -> 0 | G27: =' Inputs'!P19 -> 0 | H27: =' Inputs'!Q19 -> 0 | J27: =' Inputs'!$K$19 -> 0 | K27: =' Inputs'!$K$19 -> 0 | L27: =' Inputs'!$K$19 -> 0 | M27: =' Inputs'!$K$19 -> 0 | N27: =' Inputs'!$K$19 -> 0 | O27: =' Inputs'!$K$19 -> 0 | P27: =' Inputs'!$K$19 -> 0 | Q27: =' Inputs'!$K$19 -> 0 | ... U27: =' Inputs'!$K$19 -> 0 | V27: =' Inputs'!$L$19 -> 0 | W27: =' Inputs'!$L$19 -> 0 | X27: =' Inputs'!$L$19 -> 0 | Y27: =' Inputs'!$L$19 -> 0 | Z27: =' Inputs'!$L$19 -> 0 | AA27: =' Inputs'!$L$19 -> 0 | AB27: =' Inputs'!$L$19 -> 0 | AC27: =' Inputs'!$L$19 -> 0 | ... AG27: =' Inputs'!$L$19 -> 0 | AH27: =' Inputs'!$M$19 -> 0 | AI27: =' Inputs'!$M$19 -> 0 | AJ27: =' Inputs'!$M$19 -> 0 | AK27: =' Inputs'!$M$19 -> 0 | AL27: =' Inputs'!$M$19 -> 0 | AM27: =' Inputs'!$M$19 -> 0 | AN27: =' Inputs'!$M$19 -> 0 | AO27: =' Inputs'!$M$19 -> 0 | ... AS27: =' Inputs'!$M$19 -> 0 | AT27: =' Inputs'!$N$19 -> 0 | AU27: =' Inputs'!$N$19 -> 0 | AV27: =' Inputs'!$N$19 -> 0 | AW27: =' Inputs'!$N$19 -> 0 | AX27: =' Inputs'!$N$19 -> 0 | AY27: =' Inputs'!$N$19 -> 0 | AZ27: =' Inputs'!$N$19 -> 0 | BA27: =' Inputs'!$N$19 -> 0 | ... BE27: =' Inputs'!$N$19 -> 0 | BF27: =' Inputs'!$O$19 -> 0 | BG27: =' Inputs'!$O$19 -> 0 | BH27: =' Inputs'!$O$19 -> 0 | BI27: =' Inputs'!$O$19 -> 0 | BJ27: =' Inputs'!$O$19 -> 0 | BK27: =' Inputs'!$O$19 -> 0 | BL27: =' Inputs'!$O$19 -> 0 | BM27: =' Inputs'!$O$19 -> 0 | ... CO27: =' Inputs'!$O$19 -> 0
A28: Tickets Sold | B28: =SUM(J28:U28) -> #REF! | C28: =SUM(V28:AG28) -> #REF! | D28: =SUM(AH28:AS28) -> #REF! | E28: =SUM(AT28:BE28) -> #REF! | F28: =SUM(BF28:BQ28) -> #REF! | G28: =SUM(BR28:CC28) -> #REF! | H28: =SUM(CD28:CO28) -> #REF! | J28: =J13*' Inputs'!#REF! -> #REF! | K28: =K13*' Inputs'!#REF! -> #REF! | L28: =L13*' Inputs'!#REF! -> #REF! | M28: =M13*' Inputs'!#REF! -> #REF! | N28: =N13*' Inputs'!#REF! -> #REF! | O28: =O13*' Inputs'!#REF! -> #REF! | P28: =P13*' Inputs'!#REF! -> #REF! | Q28: =Q13*' Inputs'!#REF! -> #REF! | ... CO28: =CO13*' Inputs'!#REF! -> #REF!
A29: Total Ticket Sales | B29: =SUM(J29:U29) -> #REF! | C29: =SUM(V29:AG29) -> #REF! | D29: =SUM(AH29:AS29) -> #REF! | E29: =SUM(AT29:BE29) -> #REF! | F29: =SUM(BF29:BQ29) -> #REF! | G29: =SUM(BR29:CC29) -> #REF! | H29: =SUM(CD29:CO29) -> #REF! | J29: =J28*J27 -> #REF! | K29: =K28*K27 -> #REF! | L29: =L28*L27 -> #REF! | M29: =M28*M27 -> #REF! | N29: =N28*N27 -> #REF! | O29: =O28*O27 -> #REF! | P29: =P28*P27 -> #REF! | Q29: =Q28*Q27 -> #REF! | ... CO29: =CO28*CO27 -> #REF!
A30: Net ticket fee (-Stripe) | B30: =SUM(J30:U30) -> #REF! | C30: =SUM(V30:AG30) -> #REF! | D30: =SUM(AH30:AS30) -> #REF! | E30: =SUM(AT30:BE30) -> #REF! | F30: =SUM(BF30:BQ30) -> #REF! | G30: =SUM(BR30:CC30) -> #REF! | H30: =SUM(CD30:CO30) -> #REF! | J30: =J28*' Inputs'!$C$22 -> #REF! | K30: =K28*' Inputs'!$C$22 -> #REF! | L30: =L28*' Inputs'!$C$22 -> #REF! | M30: =M28*' Inputs'!$C$22 -> #REF! | N30: =N28*' Inputs'!$C$22 -> #REF! | O30: =O28*' Inputs'!$C$22 -> #REF! | P30: =P28*' Inputs'!$C$22 -> #REF! | Q30: =Q28*' Inputs'!$C$22 -> #REF! | ... U30: =U28*' Inputs'!$C$22 -> #REF! | V30: =V28*' Inputs'!$D$22 -> #REF! | W30: =W28*' Inputs'!$D$22 -> #REF! | X30: =X28*' Inputs'!$D$22 -> #REF! | Y30: =Y28*' Inputs'!$D$22 -> #REF! | Z30: =Z28*' Inputs'!$D$22 -> #REF! | AA30: =AA28*' Inputs'!$D$22 -> #REF! | AB30: =AB28*' Inputs'!$D$22 -> #REF! | AC30: =AC28*' Inputs'!$D$22 -> #REF! | ... AG30: =AG28*' Inputs'!$D$22 -> #REF! | AH30: =AH28*' Inputs'!$E$22 -> #REF! | AI30: =AI28*' Inputs'!$E$22 -> #REF! | AJ30: =AJ28*' Inputs'!$E$22 -> #REF! | AK30: =AK28*' Inputs'!$E$22 -> #REF! | AL30: =AL28*' Inputs'!$E$22 -> #REF! | AM30: =AM28*' Inputs'!$E$22 -> #REF! | AN30: =AN28*' Inputs'!$E$22 -> #REF! | AO30: =AO28*' Inputs'!$E$22 -> #REF! | ... AS30: =AS28*' Inputs'!$E$22 -> #REF! | AT30: =AT28*' Inputs'!$F$22 -> #REF! | AU30: =AU28*' Inputs'!$F$22 -> #REF! | AV30: =AV28*' Inputs'!$F$22 -> #REF! | AW30: =AW28*' Inputs'!$F$22 -> #REF! | AX30: =AX28*' Inputs'!$F$22 -> #REF! | AY30: =AY28*' Inputs'!$F$22 -> #REF! | AZ30: =AZ28*' Inputs'!$F$22 -> #REF! | BA30: =BA28*' Inputs'!$F$22 -> #REF! | ... BE30: =BE28*' Inputs'!$F$22 -> #REF! | BF30: =BF28*' Inputs'!$G$22 -> #REF! | BG30: =BG28*' Inputs'!$G$22 -> #REF! | BH30: =BH28*' Inputs'!$G$22 -> #REF! | BI30: =BI28*' Inputs'!$G$22 -> #REF! | BJ30: =BJ28*' Inputs'!$G$22 -> #REF! | BK30: =BK28*' Inputs'!$G$22 -> #REF! | BL30: =BL28*' Inputs'!$G$22 -> #REF! | BM30: =BM28*' Inputs'!$G$22 -> #REF! | ... BQ30: =BQ28*' Inputs'!$G$22 -> #REF! | BR30: =BR28*' Inputs'!$H$22 -> #REF! | BS30: =BS28*' Inputs'!$H$22 -> #REF! | BT30: =BT28*' Inputs'!$H$22 -> #REF! | BU30: =BU28*' Inputs'!$H$22 -> #REF! | BV30: =BV28*' Inputs'!$H$22 -> #REF! | BW30: =BW28*' Inputs'!$H$22 -> #REF! | BX30: =BX28*' Inputs'!$H$22 -> #REF! | BY30: =BY28*' Inputs'!$H$22 -> #REF! | ... CO30: =CO28*' Inputs'!$H$22 -> #REF!
A31: Net transaction fee (-Stripe) | B31: =SUM(J31:U31) -> #REF! | C31: =SUM(V31:AG31) -> #REF! | D31: =SUM(AH31:AS31) -> #REF! | E31: =SUM(AT31:BE31) -> #REF! | F31: =SUM(BF31:BQ31) -> #REF! | G31: =SUM(BR31:CC31) -> #REF! | H31: =SUM(CD31:CO31) -> #REF! | J31: =J29*' Inputs'!$C$26 -> #REF! | K31: =K29*' Inputs'!$C$26 -> #REF! | L31: =L29*' Inputs'!$C$26 -> #REF! | M31: =M29*' Inputs'!$C$26 -> #REF! | N31: =N29*' Inputs'!$C$26 -> #REF! | O31: =O29*' Inputs'!$C$26 -> #REF! | P31: =P29*' Inputs'!$C$26 -> #REF! | Q31: =Q29*' Inputs'!$C$26 -> #REF! | ... U31: =U29*' Inputs'!$C$26 -> #REF! | V31: =V29*' Inputs'!$D$26 -> #REF! | W31: =W29*' Inputs'!$D$26 -> #REF! | X31: =X29*' Inputs'!$D$26 -> #REF! | Y31: =Y29*' Inputs'!$D$26 -> #REF! | Z31: =Z29*' Inputs'!$D$26 -> #REF! | AA31: =AA29*' Inputs'!$D$26 -> #REF! | AB31: =AB29*' Inputs'!$D$26 -> #REF! | AC31: =AC29*' Inputs'!$D$26 -> #REF! | ... AG31: =AG29*' Inputs'!$D$26 -> #REF! | AH31: =AH29*' Inputs'!$E$26 -> #REF! | AI31: =AI29*' Inputs'!$E$26 -> #REF! | AJ31: =AJ29*' Inputs'!$E$26 -> #REF! | AK31: =AK29*' Inputs'!$E$26 -> #REF! | AL31: =AL29*' Inputs'!$E$26 -> #REF! | AM31: =AM29*' Inputs'!$E$26 -> #REF! | AN31: =AN29*' Inputs'!$E$26 -> #REF! | AO31: =AO29*' Inputs'!$E$26 -> #REF! | ... AS31: =AS29*' Inputs'!$E$26 -> #REF! | AT31: =AT29*' Inputs'!$F$26 -> #REF! | AU31: =AU29*' Inputs'!$F$26 -> #REF! | AV31: =AV29*' Inputs'!$F$26 -> #REF! | AW31: =AW29*' Inputs'!$F$26 -> #REF! | AX31: =AX29*' Inputs'!$F$26 -> #REF! | AY31: =AY29*' Inputs'!$F$26 -> #REF! | AZ31: =AZ29*' Inputs'!$F$26 -> #REF! | BA31: =BA29*' Inputs'!$F$26 -> #REF! | ... BE31: =BE29*' Inputs'!$F$26 -> #REF! | BF31: =BF29*' Inputs'!$G$26 -> #REF! | BG31: =BG29*' Inputs'!$G$26 -> #REF! | BH31: =BH29*' Inputs'!$G$26 -> #REF! | BI31: =BI29*' Inputs'!$G$26 -> #REF! | BJ31: =BJ29*' Inputs'!$G$26 -> #REF! | BK31: =BK29*' Inputs'!$G$26 -> #REF! | BL31: =BL29*' Inputs'!$G$26 -> #REF! | BM31: =BM29*' Inputs'!$G$26 -> #REF! | ... BQ31: =BQ29*' Inputs'!$G$26 -> #REF! | BR31: =BR29*' Inputs'!$H$26 -> #REF! | BS31: =BS29*' Inputs'!$H$26 -> #REF! | BT31: =BT29*' Inputs'!$H$26 -> #REF! | BU31: =BU29*' Inputs'!$H$26 -> #REF! | BV31: =BV29*' Inputs'!$H$26 -> #REF! | BW31: =BW29*' Inputs'!$H$26 -> #REF! | BX31: =BX29*' Inputs'!$H$26 -> #REF! | BY31: =BY29*' Inputs'!$H$26 -> #REF! | ... CO31: =CO29*' Inputs'!$H$26 -> #REF!
A32: Nigh ticket revenue | B32: =SUM(J32:U32) -> #REF! | C32: =SUM(V32:AG32) -> #REF! | D32: =SUM(AH32:AS32) -> #REF! | E32: =SUM(AT32:BE32) -> #REF! | F32: =SUM(BF32:BQ32) -> #REF! | G32: =SUM(BR32:CC32) -> #REF! | H32: =SUM(CD32:CO32) -> #REF! | J32: =J30+J31 -> #REF! | K32: =K30+K31 -> #REF! | L32: =L30+L31 -> #REF! | M32: =M30+M31 -> #REF! | N32: =N30+N31 -> #REF! | O32: =O30+O31 -> #REF! | P32: =P30+P31 -> #REF! | Q32: =Q30+Q31 -> #REF! | ... CO32: =CO30+CO31 -> #REF!
A33: Nigh take rate | B33: =B32/B29 -> #REF! | C33: =C32/C29 -> #REF! | D33: =D32/D29 -> #REF! | E33: =E32/E29 -> #REF! | F33: =F32/F29 -> #REF! | G33: =G32/G29 -> #REF! | H33: =H32/H29 -> #REF!
A35: Business subscription revenue | B35: =SUM(J35:U35) -> 0 | C35: =SUM(V35:AG35) -> 19481.622 | D35: =SUM(AH35:AS35) -> 140511.44 | E35: =SUM(AT35:BE35) -> 1350974.1 | F35: =SUM(BF35:BQ35) -> 7228049.3 | G35: =SUM(BR35:CC35) -> 38671871 | H35: =SUM(CD35:CO35) -> 2.0690418e+08 | J35: =' Inputs'!$C$29*Subscriptions!J13 -> 0 | K35: =' Inputs'!$C$29*Subscriptions!K13 -> 0 | L35: =' Inputs'!$C$29*Subscriptions!L13 -> 0 | M35: =' Inputs'!$C$29*Subscriptions!M13 -> 0 | N35: =' Inputs'!$C$29*Subscriptions!N13 -> 0 | O35: =' Inputs'!$C$29*Subscriptions!O13 -> 0 | P35: =' Inputs'!$C$29*Subscriptions!P13 -> 0 | Q35: =' Inputs'!$C$29*Subscriptions!Q13 -> 0 | ... U35: =' Inputs'!$C$29*Subscriptions!U13 -> 0 | V35: =' Inputs'!$D$29*Subscriptions!V13 -> 911.02524 | W35: =' Inputs'!$D$29*Subscriptions!W13 -> 1002.1278 | X35: =' Inputs'!$D$29*Subscriptions!X13 -> 1102.3405 | Y35: =' Inputs'!$D$29*Subscriptions!Y13 -> 1212.5746 | Z35: =' Inputs'!$D$29*Subscriptions!Z13 -> 1333.8321 | AA35: =' Inputs'!$D$29*Subscriptions!AA13 -> 1467.2153 | AB35: =' Inputs'!$D$29*Subscriptions!AB13 -> 1613.9368 | AC35: =' Inputs'!$D$29*Subscriptions!AC13 -> 1775.3305 | ... AG35: =' Inputs'!$D$29*Subscriptions!AG13 -> 2599.2613 | AH35: =' Inputs'!$E$29*Subscriptions!AH13 -> 5822.3454 | AI35: =' Inputs'!$E$29*Subscriptions!AI13 -> 6521.0269 | AJ35: =' Inputs'!$E$29*Subscriptions!AJ13 -> 7303.5501 | AK35: =' Inputs'!$E$29*Subscriptions!AK13 -> 8179.9761 | AL35: =' Inputs'!$E$29*Subscriptions!AL13 -> 9161.5732 | AM35: =' Inputs'!$E$29*Subscriptions!AM13 -> 10260.962 | AN35: =' Inputs'!$E$29*Subscriptions!AN13 -> 11492.277 | AO35: =' Inputs'!$E$29*Subscriptions!AO13 -> 12871.351 | ... AS35: =' Inputs'!$E$29*Subscriptions!AS13 -> 20253.32 | AT35: =' Inputs'!$F$29*Subscriptions!AT13 -> 46582.635 | AU35: =' Inputs'!$F$29*Subscriptions!AU13 -> 53570.03 | AV35: =' Inputs'!$F$29*Subscriptions!AV13 -> 61605.535 | AW35: =' Inputs'!$F$29*Subscriptions!AW13 -> 70846.365 | AX35: =' Inputs'!$F$29*Subscriptions!AX13 -> 81473.32 | AY35: =' Inputs'!$F$29*Subscriptions!AY13 -> 93694.318 | AZ35: =' Inputs'!$F$29*Subscriptions!AZ13 -> 107748.47 | BA35: =' Inputs'!$F$29*Subscriptions!BA13 -> 123910.74 | ... BE35: =' Inputs'!$F$29*Subscriptions!BE13 -> 216720.65 | BF35: =' Inputs'!$G$29*Subscriptions!BF13 -> 249228.75 | BG35: =' Inputs'!$G$29*Subscriptions!BG13 -> 286613.06 | BH35: =' Inputs'!$G$29*Subscriptions!BH13 -> 329605.02 | BI35: =' Inputs'!$G$29*Subscriptions!BI13 -> 379045.77 | BJ35: =' Inputs'!$G$29*Subscriptions!BJ13 -> 435902.64 | BK35: =' Inputs'!$G$29*Subscriptions!BK13 -> 501288.03 | BL35: =' Inputs'!$G$29*Subscriptions!BL13 -> 576481.24 | BM35: =' Inputs'!$G$29*Subscriptions!BM13 -> 662953.42 | ... BQ35: =' Inputs'!$G$29*Subscriptions!BQ13 -> 1159509.7 | BR35: =' Inputs'!$H$29*Subscriptions!BR13 -> 1333436.1 | BS35: =' Inputs'!$H$29*Subscriptions!BS13 -> 1533451.6 | BT35: =' Inputs'!$H$29*Subscriptions!BT13 -> 1763469.3 | BU35: =' Inputs'!$H$29*Subscriptions!BU13 -> 2027989.7 | BV35: =' Inputs'!$H$29*Subscriptions!BV13 -> 2332188.1 | BW35: =' Inputs'!$H$29*Subscriptions!BW13 -> 2682016.4 | BX35: =' Inputs'!$H$29*Subscriptions!BX13 -> 3084318.8 | BY35: =' Inputs'!$H$29*Subscriptions!BY13 -> 3546966.6 | ... CC35: =' Inputs'!$H$29*Subscriptions!CC13 -> 6203666.8 | CD35: =' Inputs'!$I$29*Subscriptions!CD13 -> 7134216.8 | CE35: =' Inputs'!$I$29*Subscriptions!CE13 -> 8204349.4 | CF35: =' Inputs'!$I$29*Subscriptions!CF13 -> 9435001.8 | CG35: =' Inputs'!$I$29*Subscriptions!CG13 -> 10850252 | CH35: =' Inputs'!$I$29*Subscriptions!CH13 -> 12477790 | CI35: =' Inputs'!$I$29*Subscriptions!CI13 -> 14349458 | CJ35: =' Inputs'!$I$29*Subscriptions!CJ13 -> 16501877 | CK35: =' Inputs'!$I$29*Subscriptions!CK13 -> 18977159 | ... CO35: =' Inputs'!$I$29*Subscriptions!CO13 -> 33191169
A37: Ad/Boost revenue | B37: =SUM(J37:U37) -> #REF! | C37: =SUM(V37:AG37) -> #REF! | D37: =SUM(AH37:AS37) -> #REF! | E37: =SUM(AT37:BE37) -> #REF! | F37: =SUM(BF37:BQ37) -> #REF! | G37: =SUM(BR37:CC37) -> #REF! | H37: =SUM(CD37:CO37) -> #REF! | J37: =J28*' Inputs'!$C$33*' Inputs'!$C$34 -> #REF! | K37: =K28*' Inputs'!$C$33*' Inputs'!$C$34 -> #REF! | L37: =L28*' Inputs'!$C$33*' Inputs'!$C$34 -> #REF! | M37: =M28*' Inputs'!$C$33*' Inputs'!$C$34 -> #REF! | N37: =N28*' Inputs'!$C$33*' Inputs'!$C$34 -> #REF! | O37: =O28*' Inputs'!$C$33*' Inputs'!$C$34 -> #REF! | P37: =P28*' Inputs'!$C$33*' Inputs'!$C$34 -> #REF! | Q37: =Q28*' Inputs'!$C$33*' Inputs'!$C$34 -> #REF! | ... U37: =U28*' Inputs'!$C$33*' Inputs'!$C$34 -> #REF! | V37: =V28*' Inputs'!$D$33*' Inputs'!$D$34 -> #REF! | W37: =W28*' Inputs'!$D$33*' Inputs'!$D$34 -> #REF! | X37: =X28*' Inputs'!$D$33*' Inputs'!$D$34 -> #REF! | Y37: =Y28*' Inputs'!$D$33*' Inputs'!$D$34 -> #REF! | Z37: =Z28*' Inputs'!$D$33*' Inputs'!$D$34 -> #REF! | AA37: =AA28*' Inputs'!$D$33*' Inputs'!$D$34 -> #REF! | AB37: =AB28*' Inputs'!$D$33*' Inputs'!$D$34 -> #REF! | AC37: =AC28*' Inputs'!$D$33*' Inputs'!$D$34 -> #REF! | ... AG37: =AG28*' Inputs'!$D$33*' Inputs'!$D$34 -> #REF! | AH37: =AH28*' Inputs'!$E$33*' Inputs'!$E$34 -> #REF! | AI37: =AI28*' Inputs'!$E$33*' Inputs'!$E$34 -> #REF! | AJ37: =AJ28*' Inputs'!$E$33*' Inputs'!$E$34 -> #REF! | AK37: =AK28*' Inputs'!$E$33*' Inputs'!$E$34 -> #REF! | AL37: =AL28*' Inputs'!$E$33*' Inputs'!$E$34 -> #REF! | AM37: =AM28*' Inputs'!$E$33*' Inputs'!$E$34 -> #REF! | AN37: =AN28*' Inputs'!$E$33*' Inputs'!$E$34 -> #REF! | AO37: =AO28*' Inputs'!$E$33*' Inputs'!$E$34 -> #REF! | ... AS37: =AS28*' Inputs'!$E$33*' Inputs'!$E$34 -> #REF! | AT37: =AT28*' Inputs'!$F$33*' Inputs'!$F$34 -> #REF! | AU37: =AU28*' Inputs'!$F$33*' Inputs'!$F$34 -> #REF! | AV37: =AV28*' Inputs'!$F$33*' Inputs'!$F$34 -> #REF! | AW37: =AW28*' Inputs'!$F$33*' Inputs'!$F$34 -> #REF! | AX37: =AX28*' Inputs'!$F$33*' Inputs'!$F$34 -> #REF! | AY37: =AY28*' Inputs'!$F$33*' Inputs'!$F$34 -> #REF! | AZ37: =AZ28*' Inputs'!$F$33*' Inputs'!$F$34 -> #REF! | BA37: =BA28*' Inputs'!$F$33*' Inputs'!$F$34 -> #REF! | ... BE37: =BE28*' Inputs'!$F$33*' Inputs'!$F$34 -> #REF! | BF37: =BF28*' Inputs'!$G$33*' Inputs'!$G$34 -> #REF! | BG37: =BG28*' Inputs'!$G$33*' Inputs'!$G$34 -> #REF! | BH37: =BH28*' Inputs'!$G$33*' Inputs'!$G$34 -> #REF! | BI37: =BI28*' Inputs'!$G$33*' Inputs'!$G$34 -> #REF! | BJ37: =BJ28*' Inputs'!$G$33*' Inputs'!$G$34 -> #REF! | BK37: =BK28*' Inputs'!$G$33*' Inputs'!$G$34 -> #REF! | BL37: =BL28*' Inputs'!$G$33*' Inputs'!$G$34 -> #REF! | BM37: =BM28*' Inputs'!$G$33*' Inputs'!$G$34 -> #REF! | ... BQ37: =BQ28*' Inputs'!$G$33*' Inputs'!$G$34 -> #REF! | BR37: =BR28*' Inputs'!$H$33*' Inputs'!$H$34 -> #REF! | BS37: =BS28*' Inputs'!$H$33*' Inputs'!$H$34 -> #REF! | BT37: =BT28*' Inputs'!$H$33*' Inputs'!$H$34 -> #REF! | BU37: =BU28*' Inputs'!$H$33*' Inputs'!$H$34 -> #REF! | BV37: =BV28*' Inputs'!$H$33*' Inputs'!$H$34 -> #REF! | BW37: =BW28*' Inputs'!$H$33*' Inputs'!$H$34 -> #REF! | BX37: =BX28*' Inputs'!$H$33*' Inputs'!$H$34 -> #REF! | BY37: =BY28*' Inputs'!$H$33*' Inputs'!$H$34 -> #REF! | ... CO37: =CO28*' Inputs'!$H$33*' Inputs'!$H$34 -> #REF!
A39: User subscription revenue | B39: =' Inputs'!C38*' Inputs'!C39*Subscriptions!B23 -> 0 | C39: =' Inputs'!D38*' Inputs'!D39*Subscriptions!C23 -> 0 | D39: =' Inputs'!E38*' Inputs'!E39*Subscriptions!D23 -> 0 | E39: =' Inputs'!F38*' Inputs'!F39*Subscriptions!E23 -> 0 | F39: =' Inputs'!G38*' Inputs'!G39*Subscriptions!F23 -> 0 | G39: =' Inputs'!H38*' Inputs'!H39*Subscriptions!G23 -> 0 | H39: =' Inputs'!I38*' Inputs'!I39*Subscriptions!H23 -> 0
A41: TOTAL REVENUE | B41: =B32+B35+B37+B39+#REF! -> #REF! | C41: =C32+C35+C37+C39+#REF! -> #REF! | D41: =D32+D35+D37+D39+#REF! -> #REF! | E41: =E32+E35+E37+E39+#REF! -> #REF! | F41: =F32+F35+F37+F39+#REF! -> #REF! | G41: =G32+G35+G37+G39+#REF! -> #REF! | H41: =H32+H35+H37+H39+#REF! -> #REF! | J41: =SUM(J32:J38) -> #REF! | K41: =SUM(K32:K38) -> #REF! | L41: =SUM(L32:L38) -> #REF! | M41: =SUM(M32:M38) -> #REF! | N41: =SUM(N32:N38) -> #REF! | O41: =SUM(O32:O38) -> #REF! | P41: =SUM(P32:P38) -> #REF! | Q41: =SUM(Q32:Q38) -> #REF! | ... CO41: =SUM(CO32:CO38) -> #REF!
A43: Avg Total Sales per Business | B43: =B29/B13 -> #REF! | C43: =C29/C13 -> #REF! | D43: =D29/D13 -> #REF! | E43: =E29/E13 -> #REF! | F43: =F29/F13 -> #REF! | G43: =G29/G13 -> #REF! | H43: =H29/H13 -> #REF! | J43: =J29/J13 -> #REF! | K43: =K29/K13 -> #REF! | L43: =L29/L13 -> #REF! | M43: =M29/M13 -> #REF! | N43: =N29/N13 -> #REF! | O43: =O29/O13 -> #REF! | P43: =P29/P13 -> #REF! | Q43: =Q29/Q13 -> #REF! | ... CO43: =CO29/CO13 -> #REF!
A44: Nigh Total Revenue per Business | B44: =B41/B13 -> #REF! | C44: =C41/C13 -> #REF! | D44: =D41/D13 -> #REF! | E44: =E41/E13 -> #REF! | F44: =F41/F13 -> #REF! | G44: =G41/G13 -> #REF! | H44: =H41/H13 -> #REF! | J44: =J41/J13 -> #REF! | K44: =K41/K13 -> #REF! | L44: =L41/L13 -> #REF! | M44: =M41/M13 -> #REF! | N44: =N41/N13 -> #REF! | O44: =O41/O13 -> #REF! | P44: =P41/P13 -> #REF! | Q44: =Q41/Q13 -> #REF! | ... CO44: =CO41/CO13 -> #REF!
A45: Nigh Revenue % of Biz Sales | B45: =B44/B43 -> #REF! | C45: =C44/C43 -> #REF! | D45: =D44/D43 -> #REF! | E45: =E44/E43 -> #REF! | F45: =F44/F43 -> #REF! | G45: =G44/G43 -> #REF! | H45: =H44/H43 -> #REF! | J45: =J44/J43 -> #REF! | K45: =K44/K43 -> #REF! | L45: =L44/L43 -> #REF! | M45: =M44/M43 -> #REF! | N45: =N44/N43 -> #REF! | O45: =O44/O43 -> #REF! | P45: =P44/P43 -> #REF! | Q45: =Q44/Q43 -> #REF! | ... CO45: =CO44/CO43 -> #REF!
A47: EXPENSES
A48: Growth
A49: Business acquisition cost | B49: =B11 -> 1573.5891 | C49: =C11 -> 2656.5849 | D49: =D11 -> 7527.3985 | E49: =E11 -> 44053.503 | F49: =F11 -> 235697.26 | G49: =G11 -> 1261039.3 | H49: =H11 -> 6746875.5
A50: User acquisition cost | B50: =B21 -> 320000 | C50: =C21 -> 601837.11 | D50: =D21 -> 7320819.4 | E50: =E21 -> 25638134 | F50: =F21 -> 39533765 | G50: =G21 -> 52556765 | H50: =H21 -> 65620966
A51: MSA launch cost | B51: =SUMIF(Merchants!$N$4:$N$11, 1, Merchants!$M$4:$M$11) -> 33075.8 | C51: =SUMIF(Merchants!$N$4:$N$11, 2, Merchants!$M$4:$M$11) -> 407799.2 | D51: =SUMIF(Merchants!$N$4:$N$11, 3, Merchants!$M$4:$M$11) -> 105956.5 | E51: =SUMIF(Merchants!$N$4:$N$11, 4, Merchants!$M$4:$M$11) -> 7370252.7 | F51: =SUMIF(Merchants!$N$4:$N$11, 5, Merchants!$M$4:$M$11) -> 10621012 | G51: =SUMIF(Merchants!$N$4:$N$11, 6, Merchants!$M$4:$M$11) -> 10322809 | H51: =SUMIF(Merchants!$N$4:$N$11, 7, Merchants!$M$4:$M$11) -> 0
A52: Operating Expenses | B52: =SUM(J52:U52) -> 673900 | C52: =SUM(V52:AG52) -> 864600 | D52: =SUM(AH52:AS52) -> #REF! | E52: =D52 -> #REF! | F52: =E52 -> #REF! | G52: =F52 -> #REF! | H52: =G52 -> #REF! | J52: ='Expenses Yr1-2'!D34 -> 42158.333 | K52: ='Expenses Yr1-2'!E34 -> 42158.333 | L52: ='Expenses Yr1-2'!F34 -> 42158.333 | M52: ='Expenses Yr1-2'!G34 -> 42158.333 | N52: ='Expenses Yr1-2'!H34 -> 42158.333 | O52: ='Expenses Yr1-2'!I34 -> 66158.333 | P52: ='Expenses Yr1-2'!J34 -> 66158.333 | Q52: ='Expenses Yr1-2'!K34 -> 66158.333 | ... AG52: ='Expenses Yr1-2'!AA34 -> 72258.333 | AH52: ='Expenses Yr1-2'!#REF! -> #REF! | AI52: ='Expenses Yr1-2'!#REF! -> #REF! | AJ52: ='Expenses Yr1-2'!#REF! -> #REF! | AK52: ='Expenses Yr1-2'!#REF! -> #REF! | AL52: ='Expenses Yr1-2'!#REF! -> #REF! | AM52: ='Expenses Yr1-2'!#REF! -> #REF! | AN52: ='Expenses Yr1-2'!#REF! -> #REF! | AO52: ='Expenses Yr1-2'!#REF! -> #REF! | ... AS52: ='Expenses Yr1-2'!#REF! -> #REF!
A53: Variable (% of rev) | B53: 0 | C53: 0 | D53: 0 | E53: =' Inputs'!C60*Subscriptions!E41 -> #REF! | F53: =F41*' Inputs'!C61 -> #REF! | G53: =' Inputs'!C62*Subscriptions!G41 -> #REF! | H53: =' Inputs'!C63*H41 -> #REF!
A55: TOTAL EXPENSES | B55: =SUM(B49:B54) -> 1028549.4 | C55: =SUM(C49:C54) -> 1876892.9 | D55: =SUM(D49:D54) -> #REF! | E55: =SUM(E49:E54) -> #REF! | F55: =SUM(F49:F54) -> #REF! | G55: =SUM(G49:G54) -> #REF! | H55: =SUM(H49:H54) -> #REF!
A57: CAPITAL
A58: NET INCOME (+/-) | B58: =B41-B55 -> #REF! | C58: =C41-C55 -> #REF! | D58: =D41-D55 -> #REF! | E58: =E41-E55 -> #REF! | F58: =F41-F55 -> #REF! | G58: =G41-G55 -> #REF! | H58: =H41-H55 -> #REF!
B60: Denver Metro | C60: Colorado | D60: Top 10 MSAs | E60: Top 50 MSAs | F60: Nationwide
A61: CAPITAL IN | B61: 3000000 | C61: 3000000 | D61: 25000000 | E61: 50000000 | F61: 50000000
A62: CASH AT START | B62: 0 | C62: =B63 -> #REF! | D62: =C63 -> #REF! | E62: =D63 -> #REF! | F62: =E63 -> #REF! | G62: =F63 -> #REF! | H62: =G63 -> #REF!
A63: CASH AT END | B63: =B62+B58+B61 -> #REF! | C63: =C62+C58+C61 -> #REF! | D63: =D62+D58+D61 -> #REF! | E63: =E62+E58+E61 -> #REF! | F63: =F62+F58+F61 -> #REF! | G63: =G62+G58+G61 -> #REF! | H63: =H62+H58+H61 -> #REF!
B64: Seed | C64: Seed+ | D64: Series A

Sheet Expenses Yr1-2
B1: 2024 | C1: 2025 | D1: =' Inputs'!B3 -> 45292 | E1: =D1+31 -> 45323 | F1: =E1+31 -> 45354 | G1: =F1+31 -> 45385 | H1: =G1+31 -> 45416 | I1: =H1+31 -> 45447 | J1: =I1+31 -> 45478 | K1: =J1+31 -> 45509 | L1: =K1+31 -> 45540 | ... AA1: =Z1+31 -> 46005
B2: Year 1 | C2: Year 2 | D2: =CONCATENATE("Month ", D3) -> Month 1 | E2: =CONCATENATE("Month ", E3) -> Month 2 | F2: =CONCATENATE("Month ", F3) -> Month 3 | G2: =CONCATENATE("Month ", G3) -> Month 4 | H2: =CONCATENATE("Month ", H3) -> Month 5 | I2: =CONCATENATE("Month ", I3) -> Month 6 | J2: =CONCATENATE("Month ", J3) -> Month 7 | K2: =CONCATENATE("Month ", K3) -> Month 8 | ... AA2: =CONCATENATE("Month ", AA3) -> Month 24
D3: 1 | E3: 2 | F3: 3 | G3: 4 | H3: 5 | I3: 6 | J3: 7 | K3: 8 | L3: 9 | M3: 10 | N3: 11 | O3: 12 | P3: 13 | Q3: 14 | R3: 15 | S3: 16 | T3: 17 | U3: 18 | V3: 19 | W3: 20 | X3: 21 | Y3: 22 | Z3: 23 | AA3: 24
A4: User Marketing
A5: Online Ads
A6: Events/Sponsorships
A7: Partnerships
A8: Total User Marketing
A10: Pro Marketing
A11: Lead Gen
A12: Mailings
A13: Events/Sponsorships
A14: Partnerships
A15: Total Pro Marketing
A17: Operating Expenses
A18: Accounting/Payroll Services | B18: =SUM(D18:O18) -> 9000 | C18: =SUM(P18:AA18) -> 12000 | D18: 750 | E18: 750 | F18: 750 | G18: 750 | H18: 750 | I18: 750 | J18: 750 | K18: 750 | L18: 750 | M18: 750 | N18: 750 | O18: 750 | P18: 1000 | Q18: 1000 | R18: 1000 | S18: 1000 | T18: 1000 | U18: 1000 | V18: 1000 | W18: 1000 | X18: 1000 | Y18: 1000 | Z18: 1000 | AA18: 1000
A19: Marketing (non-direct) | B19: =SUM(D19:O19) -> 12000 | C19: =SUM(P19:AA19) -> 18000 | D19: 1000 | E19: 1000 | F19: 1000 | G19: 1000 | H19: 1000 | I19: 1000 | J19: 1000 | K19: 1000 | L19: 1000 | M19: 1000 | N19: 1000 | O19: 1000 | P19: 1500 | Q19: 1500 | R19: 1500 | S19: 1500 | T19: 1500 | U19: 1500 | V19: 1500 | W19: 1500 | X19: 1500 | Y19: 1500 | Z19: 1500 | AA19: 1500
A20: Business Development | B20: =SUM(D20:O20) -> 6000 | C20: =SUM(P20:AA20) -> 6000 | D20: 500 | E20: 500 | F20: 500 | G20: 500 | H20: 500 | I20: 500 | J20: 500 | K20: 500 | L20: 500 | M20: 500 | N20: 500 | O20: 500 | P20: 500 | Q20: 500 | R20: 500 | S20: 500 | T20: 500 | U20: 500 | V20: 500 | W20: 500 | X20: 500 | Y20: 500 | Z20: 500 | AA20: 500
A21: Licenses, Insurance, & Fees | B21: =SUM(D21:O21) -> 1200 | C21: =SUM(P21:AA21) -> 2400 | D21: 100 | E21: 100 | F21: 100 | G21: 100 | H21: 100 | I21: 100 | J21: 100 | K21: 100 | L21: 100 | M21: 100 | N21: 100 | O21: 100 | P21: 200 | Q21: 200 | R21: 200 | S21: 200 | T21: 200 | U21: 200 | V21: 200 | W21: 200 | X21: 200 | Y21: 200 | Z21: 200 | AA21: 200
A22: Meals, Events, Team Building | B22: =SUM(D22:O22) -> 15500 | C22: =SUM(P22:AA22) -> 18000 | D22: 1000 | E22: 1000 | F22: 1000 | G22: 1000 | H22: 1000 | I22: 1500 | J22: 1500 | K22: 1500 | L22: 1500 | M22: 1500 | N22: 1500 | O22: 1500 | P22: 1500 | Q22: 1500 | R22: 1500 | S22: 1500 | T22: 1500 | U22: 1500 | V22: 1500 | W22: 1500 | X22: 1500 | Y22: 1500 | Z22: 1500 | AA22: 1500
A23: Hiring & Recruiting | B23: =SUM(D23:O23) -> 6000 | C23: =SUM(P23:AA23) -> 6000 | D23: 500 | E23: 500 | F23: 500 | G23: 500 | H23: 500 | I23: 500 | J23: 500 | K23: 500 | L23: 500 | M23: 500 | N23: 500 | O23: 500 | P23: 500 | Q23: 500 | R23: 500 | S23: 500 | T23: 500 | U23: 500 | V23: 500 | W23: 500 | X23: 500 | Y23: 500 | Z23: 500 | AA23: 500
A24: Legal Services & Patents | B24: =SUM(D24:O24) -> 12000 | C24: =SUM(P24:AA24) -> 12000 | D24: 1000 | E24: 1000 | F24: 1000 | G24: 1000 | H24: 1000 | I24: 1000 | J24: 1000 | K24: 1000 | L24: 1000 | M24: 1000 | N24: 1000 | O24: 1000 | P24: 1000 | Q24: 1000 | R24: 1000 | S24: 1000 | T24: 1000 | U24: 1000 | V24: 1000 | W24: 1000 | X24: 1000 | Y24: 1000 | Z24: 1000 | AA24: 1000
A25: Subscriptions | B25: =SUM(D25:O25) -> 1200 | C25: =SUM(P25:AA25) -> 1800 | D25: 100 | E25: 100 | F25: 100 | G25: 100 | H25: 100 | I25: 100 | J25: 100 | K25: 100 | L25: 100 | M25: 100 | N25: 100 | O25: 100 | P25: 150 | Q25: 150 | R25: 150 | S25: 150 | T25: 150 | U25: 150 | V25: 150 | W25: 150 | X25: 150 | Y25: 150 | Z25: 150 | AA25: 150
A26: Office Rent & Facilities | B26: =SUM(D26:O26) -> 30000 | C26: =SUM(P26:AA26) -> 30000 | D26: 2500 | E26: 2500 | F26: 2500 | G26: 2500 | H26: 2500 | I26: 2500 | J26: 2500 | K26: 2500 | L26: 2500 | M26: 2500 | N26: 2500 | O26: 2500 | P26: 2500 | Q26: 2500 | R26: 2500 | S26: 2500 | T26: 2500 | U26: 2500 | V26: 2500 | W26: 2500 | X26: 2500 | Y26: 2500 | Z26: 2500 | AA26: 2500
A27: Office Supplies & Misc | B27: =SUM(D27:O27) -> 2400 | C27: =SUM(P27:AA27) -> 2400 | D27: 200 | E27: 200 | F27: 200 | G27: 200 | H27: 200 | I27: 200 | J27: 200 | K27: 200 | L27: 200 | M27: 200 | N27: 200 | O27: 200 | P27: 200 | Q27: 200 | R27: 200 | S27: 200 | T27: 200 | U27: 200 | V27: 200 | W27: 200 | X27: 200 | Y27: 200 | Z27: 200 | AA27: 200
A28: Technology & Equipment | B28: =SUM(D28:O28) -> 3600 | C28: =SUM(P28:AA28) -> 3600 | D28: 300 | E28: 300 | F28: 300 | G28: 300 | H28: 300 | I28: 300 | J28: 300 | K28: 300 | L28: 300 | M28: 300 | N28: 300 | O28: 300 | P28: 300 | Q28: 300 | R28: 300 | S28: 300 | T28: 300 | U28: 300 | V28: 300 | W28: 300 | X28: 300 | Y28: 300 | Z28: 300 | AA28: 300
A29: Technology/SaaS Subscriptions | B29: =SUM(D29:O29) -> 27500 | C29: =SUM(P29:AA29) -> 39500 | D29: 2000 | E29: 2000 | F29: 2000 | G29: 2000 | H29: 2000 | I29: 2500 | J29: 2500 | K29: 2500 | L29: 2500 | M29: 2500 | N29: 2500 | O29: 2500 | P29: 3000 | Q29: 3000 | R29: 3000 | S29: 3000 | T29: 3000 | U29: 3500 | V29: 3500 | W29: 3500 | X29: 3500 | Y29: 3500 | Z29: 3500 | AA29: 3500
A30: Travel Expenses | B30: =SUM(D30:O30) -> 6000 | C30: =SUM(P30:AA30) -> 6000 | D30: 500 | E30: 500 | F30: 500 | G30: 500 | H30: 500 | I30: 500 | J30: 500 | K30: 500 | L30: 500 | M30: 500 | N30: 500 | O30: 500 | P30: 500 | Q30: 500 | R30: 500 | S30: 500 | T30: 500 | U30: 500 | V30: 500 | W30: 500 | X30: 500 | Y30: 500 | Z30: 500 | AA30: 500
A31: Team (Salary+Load) | B31: =SUM(D31:O31) -> 541500 | C31: =SUM(P31:AA31) -> 706900 | D31: ='Headcount Yr1-2'!K18 -> 31708.333 | E31: ='Headcount Yr1-2'!L18 -> 31708.333 | F31: ='Headcount Yr1-2'!M18 -> 31708.333 | G31: ='Headcount Yr1-2'!N18 -> 31708.333 | H31: ='Headcount Yr1-2'!O18 -> 31708.333 | I31: ='Headcount Yr1-2'!P18 -> 54708.333 | J31: ='Headcount Yr1-2'!Q18 -> 54708.333 | K31: ='Headcount Yr1-2'!R18 -> 54708.333 | ... AA31: ='Headcount Yr1-2'!AH18 -> 58908.333
A34: TOTAL EXPENSES | B34: =SUM(D34:O34) -> 673900 | C34: =SUM(P34:AA34) -> 864600 | D34: =SUM(D17:D33) -> 42158.333 | E34: =SUM(E17:E33) -> 42158.333 | F34: =SUM(F17:F33) -> 42158.333 | G34: =SUM(G17:G33) -> 42158.333 | H34: =SUM(H18:H31) -> 42158.333 | I34: =SUM(I18:I31) -> 66158.333 | J34: =SUM(J18:J31) -> 66158.333 | K34: =SUM(K18:K31) -> 66158.333 | L34: =SUM(L18:L31) -> 66158.333 | M34: =SUM(M18:M31) -> 66158.333 | N34: =SUM(N18:N31) -> 66158.333 | O34: =SUM(O18:O31) -> 66158.333 | ... AA34: =SUM(AA18:AA31) -> 72258.333

Sheet Headcount Yr1-2
D1: 2024 | E1: 2025 | G1: 2024 | H1: 2025 | I1: 2024 | J1: 2025 | K1: =' Inputs'!B3 -> 45292 | L1: =K1+31 -> 45323 | M1: =L1+31 -> 45354 | N1: =M1+31 -> 45385 | O1: =N1+31 -> 45416 | P1: =O1+31 -> 45447 | Q1: =P1+31 -> 45478 | R1: =Q1+31 -> 45509 | S1: =R1+31 -> 45540 | ... AH1: =AG1+31 -> 46005
A2: Team | B2: Role | C2: Team Member | D2: Salary | E2: Salary | F2: Load | G2: Monthly | H2: Monthly | I2: Year 1 | J2: Year 2 | K2: =CONCATENATE("Month ", K3) -> Month 1 | L2: =CONCATENATE("Month ", L3) -> Month 2 | M2: =CONCATENATE("Month ", M3) -> Month 3 | N2: =CONCATENATE("Month ", N3) -> Month 4 | O2: =CONCATENATE("Month ", O3) -> Month 5 | P2: =CONCATENATE("Month ", P3) -> Month 6 | Q2: =CONCATENATE("Month ", Q3) -> Month 7 | R2: =CONCATENATE("Month ", R3) -> Month 8 | ... AH2: =CONCATENATE("Month ", AH3) -> Month 24
K3: 1 | L3: 2 | M3: 3 | N3: 4 | O3: 5 | P3: 6 | Q3: 7 | R3: 8 | S3: 9 | T3: 10 | U3: 11 | V3: 12 | W3: 13 | X3: 14 | Y3: 15 | Z3: 16 | AA3: 17 | AB3: 18 | AC3: 19 | AD3: 20 | AE3: 21 | AF3: 22 | AG3: 23 | AH3: 24
A4: Engineering/Product | B4: Senior Software Engineer | C4: Andy | D4: 65000 | E4: 70000 | F4: 0.2 | G4: =D4*(1+F4)/12 -> 6500 | H4: =E4*(1+F4)/12 -> 7000 | I4: =SUM(K4:V4) -> 78000 | J4: =SUM(W4:AH4) -> 84000 | K4: =$G4 -> 6500 | L4: =$G4 -> 6500 | M4: =$G4 -> 6500 | N4: =$G4 -> 6500 | O4: =$G4 -> 6500 | P4: =$G4 -> 6500 | Q4: =$G4 -> 6500 | R4: =$G4 -> 6500 | ... V4: =$G4 -> 6500 | W4: =$H4 -> 7000 | X4: =$H4 -> 7000 | Y4: =$H4 -> 7000 | Z4: =$H4 -> 7000 | AA4: =$H4 -> 7000 | AB4: =$H4 -> 7000 | AC4: =$H4 -> 7000 | AD4: =$H4 -> 7000 | ... AH4: =$H4 -> 7000
A5: Engineering/Product | B5: Software Engineer | C5: OPEN | D5: 60000 | E5: 60000 | F5: 0.2 | G5: =D5*(1+F5)/12 -> 6000 | H5: =E5*(1+F5)/12 -> 6000 | I5: =SUM(K5:V5) -> 42000 | J5: =SUM(W5:AH5) -> 72000 | P5: =$G5 -> 6000 | Q5: =$G5 -> 6000 | R5: =$G5 -> 6000 | S5: =$G5 -> 6000 | T5: =$G5 -> 6000 | U5: =$G5 -> 6000 | V5: =$G5 -> 6000 | W5: =$H5 -> 6000 | X5: =$H5 -> 6000 | Y5: =$H5 -> 6000 | Z5: =$H5 -> 6000 | AA5: =$H5 -> 6000 | AB5: =$H5 -> 6000 | AC5: =$H5 -> 6000 | AD5: =$H5 -> 6000 | ... AH5: =$H5 -> 6000
A6: Engineering/Product | B6: Software Engineer | C6: OPEN | D6: 60000 | E6: 60000 | F6: 0.2 | G6: =D6*(1+F6)/12 -> 6000 | H6: =E6*(1+F6)/12 -> 6000 | I6: =SUM(K6:V6) -> 42000 | J6: =SUM(W6:AH6) -> 72000 | P6: =$G6 -> 6000 | Q6: =$G6 -> 6000 | R6: =$G6 -> 6000 | S6: =$G6 -> 6000 | T6: =$G6 -> 6000 | U6: =$G6 -> 6000 | V6: =$G6 -> 6000 | W6: =$H6 -> 6000 | X6: =$H6 -> 6000 | Y6: =$H6 -> 6000 | Z6: =$H6 -> 6000 | AA6: =$H6 -> 6000 | AB6: =$H6 -> 6000 | AC6: =$H6 -> 6000 | AD6: =$H6 -> 6000 | ... AH6: =$H6 -> 6000
A7: Engineering/Product | B7: Sr Software Engineer-India | C7: Sid | D7: 18000 | E7: 20000 | F7: 0.1 | G7: =D7*(1+F7)/12 -> 1650 | H7: =E7*(1+F7)/12 -> 1833.3333 | I7: =SUM(K7:V7) -> 19800 | J7: =SUM(W7:AH7) -> 22000 | K7: =$G7 -> 1650 | L7: =$G7 -> 1650 | M7: =$G7 -> 1650 | N7: =$G7 -> 1650 | O7: =$G7 -> 1650 | P7: =$G7 -> 1650 | Q7: =$G7 -> 1650 | R7: =$G7 -> 1650 | ... V7: =$G7 -> 1650 | W7: =$H7 -> 1833.3333 | X7: =$H7 -> 1833.3333 | Y7: =$H7 -> 1833.3333 | Z7: =$H7 -> 1833.3333 | AA7: =$H7 -> 1833.3333 | AB7: =$H7 -> 1833.3333 | AC7: =$H7 -> 1833.3333 | AD7: =$H7 -> 1833.3333 | ... AH7: =$H7 -> 1833.3333
A8: Engineering/Product | B8: Software Engineer-India | C8: Raghu | D8: 12000 | E8: 15000 | F8: 0.1 | G8: =D8*(1+F8)/12 -> 1100 | H8: =E8*(1+F8)/12 -> 1375 | I8: =SUM(K8:V8) -> 13200 | J8: =SUM(W8:AH8) -> 16500 | K8: =$G8 -> 1100 | L8: =$G8 -> 1100 | M8: =$G8 -> 1100 | N8: =$G8 -> 1100 | O8: =$G8 -> 1100 | P8: =$G8 -> 1100 | Q8: =$G8 -> 1100 | R8: =$G8 -> 1100 | ... V8: =$G8 -> 1100 | W8: =$H8 -> 1375 | X8: =$H8 -> 1375 | Y8: =$H8 -> 1375 | Z8: =$H8 -> 1375 | AA8: =$H8 -> 1375 | AB8: =$H8 -> 1375 | AC8: =$H8 -> 1375 | AD8: =$H8 -> 1375 | ... AH8: =$H8 -> 1375
A9: Engineering/Product | B9: Software Engineer-India | C9: Pavan | D9: 10000 | E9: 12000 | F9: 0.1 | G9: =D9*(1+F9)/12 -> 916.66667 | H9: =E9*(1+F9)/12 -> 1100 | I9: =SUM(K9:V9) -> 11000 | J9: =SUM(W9:AH9) -> 13200 | K9: =$G9 -> 916.66667 | L9: =$G9 -> 916.66667 | M9: =$G9 -> 916.66667 | N9: =$G9 -> 916.66667 | O9: =$G9 -> 916.66667 | P9: =$G9 -> 916.66667 | Q9: =$G9 -> 916.66667 | R9: =$G9 -> 916.66667 | ... V9: =$G9 -> 916.66667 | W9: =$H9 -> 1100 | X9: =$H9 -> 1100 | Y9: =$H9 -> 1100 | Z9: =$H9 -> 1100 | AA9: =$H9 -> 1100 | AB9: =$H9 -> 1100 | AC9: =$H9 -> 1100 | AD9: =$H9 -> 1100 | ... AH9: =$H9 -> 1100
A10: Engineering/Product | B10: Software Engineer-India | C10: Sandy | D10: 10000 | E10: 12000 | F10: 0.1 | G10: =D10*(1+F10)/12 -> 916.66667 | H10: =E10*(1+F10)/12 -> 1100 | I10: =SUM(K10:V10) -> 11000 | J10: =SUM(W10:AH10) -> 13200 | K10: =$G10 -> 916.66667 | L10: =$G10 -> 916.66667 | M10: =$G10 -> 916.66667 | N10: =$G10 -> 916.66667 | O10: =$G10 -> 916.66667 | P10: =$G10 -> 916.66667 | Q10: =$G10 -> 916.66667 | R10: =$G10 -> 916.66667 | ... V10: =$G10 -> 916.66667 | W10: =$H10 -> 1100 | X10: =$H10 -> 1100 | Y10: =$H10 -> 1100 | Z10: =$H10 -> 1100 | AA10: =$H10 -> 1100 | AB10: =$H10 -> 1100 | AC10: =$H10 -> 1100 | AD10: =$H10 -> 1100 | ... AH10: =$H10 -> 1100
A11: Engineering/Product | B11: Senior Product Manager | C11: Christian | D11: 55000 | E11: 60000 | F11: 0.1 | G11: =D11*(1+F11)/12 -> 5041.6667 | H11: =E11*(1+F11)/12 -> 5500 | I11: =SUM(K11:V11) -> 60500 | J11: =SUM(W11:AH11) -> 66000 | K11: =$G11 -> 5041.6667 | L11: =$G11 -> 5041.6667 | M11: =$G11 -> 5041.6667 | N11: =$G11 -> 5041.6667 | O11: =$G11 -> 5041.6667 | P11: =$G11 -> 5041.6667 | Q11: =$G11 -> 5041.6667 | R11: =$G11 -> 5041.6667 | ... V11: =$G11 -> 5041.6667 | W11: =$H11 -> 5500 | X11: =$H11 -> 5500 | Y11: =$H11 -> 5500 | Z11: =$H11 -> 5500 | AA11: =$H11 -> 5500 | AB11: =$H11 -> 5500 | AC11: =$H11 -> 5500 | AD11: =$H11 -> 5500 | ... AH11: =$H11 -> 5500
A12: Engineering/Product | B12: Product Manager | C12: OPEN | D12: 55000 | E12: 60000 | F12: 0.2 | G12: =D12*(1+F12)/12 -> 5500 | H12: =E12*(1+F12)/12 -> 6000 | I12: =SUM(K12:V12) -> 38500 | J12: =SUM(W12:AH12) -> 72000 | P12: =$G12 -> 5500 | Q12: =$G12 -> 5500 | R12: =$G12 -> 5500 | S12: =$G12 -> 5500 | T12: =$G12 -> 5500 | U12: =$G12 -> 5500 | V12: =$G12 -> 5500 | W12: =$H12 -> 6000 | X12: =$H12 -> 6000 | Y12: =$H12 -> 6000 | Z12: =$H12 -> 6000 | AA12: =$H12 -> 6000 | AB12: =$H12 -> 6000 | AC12: =$H12 -> 6000 | AD12: =$H12 -> 6000 | ... AH12: =$H12 -> 6000
A13: Marketing/Sales | B13: Growth Lead | C13: Jack | D13: 55000 | E13: 60000 | F13: 0.1 | G13: =D13*(1+F13)/12 -> 5041.6667 | H13: =E13*(1+F13)/12 -> 5500 | I13: =SUM(K13:V13) -> 60500 | J13: =SUM(W13:AH13) -> 66000 | K13: =$G13 -> 5041.6667 | L13: =$G13 -> 5041.6667 | M13: =$G13 -> 5041.6667 | N13: =$G13 -> 5041.6667 | O13: =$G13 -> 5041.6667 | P13: =$G13 -> 5041.6667 | Q13: =$G13 -> 5041.6667 | R13: =$G13 -> 5041.6667 | ... V13: =$G13 -> 5041.6667 | W13: =$H13 -> 5500 | X13: =$H13 -> 5500 | Y13: =$H13 -> 5500 | Z13: =$H13 -> 5500 | AA13: =$H13 -> 5500 | AB13: =$H13 -> 5500 | AC13: =$H13 -> 5500 | AD13: =$H13 -> 5500 | ... AH13: =$H13 -> 5500
A14: Marketing/Sales | B14: Biz Dev Lead | C14: Addy | D14: 55000 | E14: 60000 | F14: 0.2 | G14: =D14*(1+F14)/12 -> 5500 | H14: =E14*(1+F14)/12 -> 6000 | I14: =SUM(K14:V14) -> 66000 | J14: =SUM(W14:AH14) -> 72000 | K14: =$G14 -> 5500 | L14: =$G14 -> 5500 | M14: =$G14 -> 5500 | N14: =$G14 -> 5500 | O14: =$G14 -> 5500 | P14: =$G14 -> 5500 | Q14: =$G14 -> 5500 | R14: =$G14 -> 5500 | ... V14: =$G14 -> 5500 | W14: =$H14 -> 6000 | X14: =$H14 -> 6000 | Y14: =$H14 -> 6000 | Z14: =$H14 -> 6000 | AA14: =$H14 -> 6000 | AB14: =$H14 -> 6000 | AC14: =$H14 -> 6000 | AD14: =$H14 -> 6000 | ... AH14: =$H14 -> 6000
A15: Marketing/Sales | B15: Community Lead | C15: Sam | D15: 55000 | E15: 60000 | F15: 0.1 | G15: =D15*(1+F15)/12 -> 5041.6667 | H15: =E15*(1+F15)/12 -> 5500 | I15: =SUM(K15:V15) -> 60500 | J15: =SUM(W15:AH15) -> 66000 | K15: =$G15 -> 5041.6667 | L15: =$G15 -> 5041.6667 | M15: =$G15 -> 5041.6667 | N15: =$G15 -> 5041.6667 | O15: =$G15 -> 5041.6667 | P15: =$G15 -> 5041.6667 | Q15: =$G15 -> 5041.6667 | R15: =$G15 -> 5041.6667 | ... V15: =$G15 -> 5041.6667 | W15: =$H15 -> 5500 | X15: =$H15 -> 5500 | Y15: =$H15 -> 5500 | Z15: =$H15 -> 5500 | AA15: =$H15 -> 5500 | AB15: =$H15 -> 5500 | AC15: =$H15 -> 5500 | AD15: =$H15 -> 5500 | ... AH15: =$H15 -> 5500
A16: Marketing/Sales | B16: Social Media Lead | C16: OPEN | D16: 55000 | E16: 60000 | F16: 0.2 | G16: =D16*(1+F16)/12 -> 5500 | H16: =E16*(1+F16)/12 -> 6000 | I16: =SUM(K16:V16) -> 38500 | J16: =SUM(W16:AH16) -> 72000 | P16: =$G16 -> 5500 | Q16: =$G16 -> 5500 | R16: =$G16 -> 5500 | S16: =$G16 -> 5500 | T16: =$G16 -> 5500 | U16: =$G16 -> 5500 | V16: =$G16 -> 5500 | W16: =$H16 -> 6000 | X16: =$H16 -> 6000 | Y16: =$H16 -> 6000 | Z16: =$H16 -> 6000 | AA16: =$H16 -> 6000 | AB16: =$H16 -> 6000 | AC16: =$H16 -> 6000 | AD16: =$H16 -> 6000 | ... AH16: =$H16 -> 6000
A18: TOTAL | D18: =SUM(D4:D16) -> 565000 | E18: =SUM(E4:E16) -> 609000 | G18: =SUM(G4:G16) -> 54708.333 | H18: =SUM(H4:H16) -> 58908.333 | I18: =SUM(I4:I16) -> 541500 | J18: =SUM(J4:J16) -> 706900 | K18: =SUM(K4:K16) -> 31708.333 | L18: =SUM(L4:L16) -> 31708.333 | M18: =SUM(M4:M16) -> 31708.333 | N18: =SUM(N4:N16) -> 31708.333 | ... AH18: =SUM(AH4:AH16) -> 58908.333

Sheet Charts

Sheet Merchants
D2: NIGH MERCHANT % MARKET PENTRATION BY METRO EOY
A3: U.S. Metro | B3: Launch Tier | D3: 2024 | E3: =D3+1 -> 2025 | F3: =E3+1 -> 2026 | G3: =F3+1 -> 2027 | H3: =G3+1 -> 2028 | I3: =H3+1 -> 2029 | J3: =I3+1 -> 2030 | L3: # of MSAs | M3: Launch Cost | N3: Launch Year
A4: Boulder Metro | B4: 1 | D4: 0.1 | E4: 0.2 | F4: 0.1 | G4: 0.13 | H4: 0.18 | I4: 0.2 | J4: 0.25 | L4: 1 | M4: =SUMIF(MSAs!I$2:I$70, 1, MSAs!J$2:J$70) -> 33075.8 | N4: 1
A5: Denver Metro | B5: 2 | D5: 0 | E5: 0.02 | F5: 0.07 | G5: 0.1 | H5: 0.13 | I5: 0.18 | J5: 0.25 | L5: 1 | M5: =SUMIF(MSAs!I$2:I$70, 2, MSAs!J$2:J$70) -> 296382.1 | N5: 2
A6: Fort Collins Metro | B6: 3 | D6: 0 | E6: 0.02 | F6: 0.07 | G6: 0.1 | H6: 0.13 | I6: 0.18 | J6: 0.25 | L6: 1 | M6: =SUMIF(MSAs!I$2:I$70, 3, MSAs!J$2:J$70) -> 35906.6 | N6: 2
A7: Colorado Springs Metro | B7: 4 | D7: 0 | E7: 0.02 | F7: 0.07 | G7: 0.1 | H7: 0.13 | I7: 0.18 | J7: 0.25 | L7: 1 | M7: =SUMIF(MSAs!I$2:I$70, 4, MSAs!J$2:J$70) -> 75510.5 | N7: 2
A8: Rest of Colorado | B8: 5 | D8: 0 | E8: 0 | F8: 0.02 | G8: 0.07 | H8: 0.1 | I8: 0.13 | J8: 0.18 | L8: =COUNTIF(MSAs!I$2:I$70, 5) -> 10 | M8: =SUMIF(MSAs!I$2:I$70, 5, MSAs!J$2:J$70) -> 105956.5 | N8: 3
A9: Tier 1 MSAs | B9: 6 | D9: 0 | E9: 0 | F9: 0 | G9: 0.02 | H9: 0.07 | I9: 0.1 | J9: 0.2 | L9: =COUNTIF(MSAs!I$2:I$70, 6) -> 9 | M9: =SUMIF(MSAs!I$2:I$70, 6, MSAs!J$2:J$70) -> 7370252.7 | N9: 4
A10: Tier 2 MSAs | B10: 7 | D10: 0 | E10: 0 | F10: 0 | G10: 0 | H10: 0.02 | I10: 0.07 | J10: 0.15 | L10: =COUNTIF(MSAs!I$2:I$70, 7) -> 40 | M10: =SUMIF(MSAs!I$2:I$70, 7, MSAs!J$2:J$70) -> 10621012 | N10: 5
A11: Tier 3 MSAs | B11: 8 | D11: 0 | E11: 0 | F11: 0 | G11: 0 | H11: 0 | I11: 0.02 | J11: 0.1 | L11: nationwide | M11: =SUMIF(MSAs!I$2:I$70, 8, MSAs!J$2:J$70) -> 10322809 | N11: 6
D13: TOTAL MERCHANTS ACQUIRED BY METRO EOY
A14: U.S. Metro | B14: TOTAL MERCHANTS | D14: =D3 -> 2024 | E14: =E3 -> 2025 | F14: =F3 -> 2026 | G14: =G3 -> 2027 | H14: =H3 -> 2028 | I14: =I3 -> 2029 | J14: =J3 -> 2030
A15: Boulder Metro | B15: =SUMIF(MSAs!$I$2:$I$65,Merchants!$B4,MSAs!$D$2:$D$65) -> 2689.2 | D15: =$B15*D4 -> 268.92 | E15: =$B15*E4 -> 537.84 | F15: =$B15*F4 -> 268.92 | G15: =$B15*G4 -> 349.596 | H15: =$B15*H4 -> 484.056 | I15: =$B15*I4 -> 537.84 | J15: =$B15*J4 -> 672.3
A16: Denver Metro | B16: =SUMIF(MSAs!$I$2:$I$65,Merchants!$B5,MSAs!$D$2:$D$65) -> 19015.68 | D16: =$B16*D5 -> 0 | E16: =$B16*E5 -> 380.3136 | F16: =$B16*F5 -> 1331.0976 | G16: =$B16*G5 -> 1901.568 | H16: =$B16*H5 -> 2472.0384 | I16: =$B16*I5 -> 3422.8224 | J16: =$B16*J5 -> 4753.92
A17: Fort Collins Metro | B17: =SUMIF(MSAs!$I$2:$I$65,Merchants!$B6,MSAs!$D$2:$D$65) -> 2536.64 | D17: =$B17*D6 -> 0 | E17: =$B17*E6 -> 50.7328 | F17: =$B17*F6 -> 177.5648 | G17: =$B17*G6 -> 253.664 | H17: =$B17*H6 -> 329.7632 | I17: =$B17*I6 -> 456.5952 | J17: =$B17*J6 -> 634.16
A18: Colorado Springs Metro | B18: =SUMIF(MSAs!$I$2:$I$65,Merchants!$B7,MSAs!$D$2:$D$65) -> 4172.58 | D18: =$B18*D7 -> 0 | E18: =$B18*E7 -> 83.4516 | F18: =$B18*F7 -> 292.0806 | G18: =$B18*G7 -> 417.258 | H18: =$B18*H7 -> 542.4354 | I18: =$B18*I7 -> 751.0644 | J18: =$B18*J7 -> 1043.145
A19: Rest of Colorado | B19: =SUMIF(MSAs!$I$2:$I$65,Merchants!$B8,MSAs!$D$2:$D$65) -> 6096.94 | D19: =$B19*D8 -> 0 | E19: =$B19*E8 -> 0 | F19: =$B19*F8 -> 121.9388 | G19: =$B19*G8 -> 426.7858 | H19: =$B19*H8 -> 609.694 | I19: =$B19*I8 -> 792.6022 | J19: =$B19*J8 -> 1097.4492
A20: Tier 1 MSAs | B20: =SUMIF(MSAs!$I$2:$I$65,Merchants!$B9,MSAs!$D$2:$D$65) -> 541238 | D20: =$B20*D9 -> 0 | E20: =$B20*E9 -> 0 | F20: =$B20*F9 -> 0 | G20: =$B20*G9 -> 10824.76 | H20: =$B20*H9 -> 37886.66 | I20: =$B20*I9 -> 54123.8 | J20: =$B20*J9 -> 108247.6
A21: Tier 2 MSAs | B21: =SUMIF(MSAs!$I$2:$I$65,Merchants!$B10,MSAs!$D$2:$D$65) -> 631688 | D21: =$B21*D10 -> 0 | E21: =$B21*E10 -> 0 | F21: =$B21*F10 -> 0 | G21: =$B21*G10 -> 0 | H21: =$B21*H10 -> 12633.76 | I21: =$B21*I10 -> 44218.16 | J21: =$B21*J10 -> 94753.2
A22: Tier 3 MSAs | B22: =MSAs!D70 -> 806800 | D22: =$B22*D11 -> 0 | E22: =$B22*E11 -> 0 | F22: =$B22*F11 -> 0 | G22: =$B22*G11 -> 0 | H22: =$B22*H11 -> 0 | I22: =$B22*I11 -> 16136 | J22: =$B22*J11 -> 80680
A23: TOTAL MERCHANTS IN MSAs | B23: =SUM(B15:B22) -> 2014237 | D23: =SUM(D15:D22) -> 268.92 | E23: =SUM(E15:E22) -> 1052.338 | F23: =SUM(F15:F22) -> 2191.6018 | G23: =SUM(G15:G22) -> 14173.632 | H23: =SUM(H15:H22) -> 54958.407 | I23: =SUM(I15:I22) -> 120438.88 | J23: =SUM(J15:J22) -> 291881.77

Sheet Users
D2: NIGH USER % MARKET PENTRATION BY METRO EOY
A3: U.S. Metro | B3: Launch Tier | D3: 2024 | E3: =D3+1 -> 2025 | F3: =E3+1 -> 2026 | G3: =F3+1 -> 2027 | H3: =G3+1 -> 2028 | I3: =H3+1 -> 2029 | J3: =I3+1 -> 2030
A4: Boulder Metro | B4: 1 | D4: 0.05 | E4: 0.1 | F4: 0.15 | G4: 0.2 | H4: 0.23 | I4: 0.27 | J4: 0.3
A5: Denver Metro | B5: 2 | D5: 0.01 | E5: 0.02 | F5: 0.1 | G5: 0.15 | H5: 0.25 | I5: 0.3 | J5: 0.4
A6: Fort Collins Metro | B6: 3 | D6: 0 | E6: 0.01 | F6: 0.05 | G6: 0.1 | H6: 0.15 | I6: 0.18 | J6: 0.2
A7: Colorado Springs Metro | B7: 4 | D7: 0 | E7: 0.01 | F7: 0.05 | G7: 0.1 | H7: 0.15 | I7: 0.18 | J7: 0.2
A8: Rest of Colorado | B8: 5 | D8: 0 | E8: 0 | F8: 0.01 | G8: 0.05 | H8: 0.1 | I8: 0.15 | J8: 0.2
A9: Tier 1 MSAs | B9: 6 | D9: 0 | E9: 0 | F9: 0.01 | G9: 0.05 | H9: 0.08 | I9: 0.12 | J9: 0.15
A10: Tier 2 MSAs | B10: 7 | D10: 0 | E10: 0 | F10: 0 | G10: 0.01 | H10: 0.05 | I10: 0.08 | J10: 0.15
A11: Tier 3 MSAs | B11: 8 | D11: 0 | E11: 0 | F11: 0 | G11: 0 | H11: 0.01 | I11: 0.05 | J11: 0.08
D14: TOTAL USERS ACQUIRED BY METRO EOY
B15: Population | D15: =D3 -> 2024 | E15: =E3 -> 2025 | F15: =F3 -> 2026 | G15: =G3 -> 2027 | H15: =H3 -> 2028 | I15: =I3 -> 2029 | J15: =J3 -> 2030
A16: Boulder Metro | B16: =MSAs!C2 -> 330758 | D16: =$B16*D4 -> 16537.9 | E16: =$B16*E4 -> 33075.8 | F16: =$B16*F4 -> 49613.7 | G16: =$B16*G4 -> 66151.6 | H16: =$B16*H4 -> 76074.34 | I16: =$B16*I4 -> 89304.66 | J16: =$B16*J4 -> 99227.4
A17: Denver Metro | B17: =MSAs!C3 -> 2963821 | D17: =$B17*D5 -> 29638.21 | E17: =$B17*E5 -> 59276.42 | F17: =$B17*F5 -> 296382.1 | G17: =$B17*G5 -> 444573.15 | H17: =$B17*H5 -> 740955.25 | I17: =$B17*I5 -> 889146.3 | J17: =$B17*J5 -> 1185528.4
A18: Fort Collins Metro | B18: =MSAs!C5 -> 359066 | D18: =$B18*D6 -> 0 | E18: =$B18*E6 -> 3590.66 | F18: =$B18*F6 -> 17953.3 | G18: =$B18*G6 -> 35906.6 | H18: =$B18*H6 -> 53859.9 | I18: =$B18*I6 -> 64631.88 | J18: =$B18*J6 -> 71813.2
A19: Colorado Springs Metro | B19: =MSAs!C4 -> 755105 | D19: =$B19*D7 -> 0 | E19: =$B19*E7 -> 7551.05 | F19: =$B19*F7 -> 37755.25 | G19: =$B19*G7 -> 75510.5 | H19: =$B19*H7 -> 113265.75 | I19: =$B19*I7 -> 135918.9 | J19: =$B19*J7 -> 151021
A20: Rest of Colorado | B20: =SUM(MSAs!C6:C15) -> 1059565 | D20: =$B20*D8 -> 0 | E20: =$B20*E8 -> 0 | F20: =$B20*F8 -> 10595.65 | G20: =$B20*G8 -> 52978.25 | H20: =$B20*H8 -> 105956.5 | I20: =$B20*I8 -> 158934.75 | J20: =$B20*J8 -> 211913
A21: Tier 1 MSAs | B21: =SUMIF(MSAs!$I$2:$I$65,Users!B9,MSAs!$C$2:$C$65) -> 73702527 | D21: =$B21*D9 -> 0 | E21: =$B21*E9 -> 0 | F21: =$B21*F9 -> 737025.27 | G21: =$B21*G9 -> 3685126.4 | H21: =$B21*H9 -> 5896202.2 | I21: =$B21*I9 -> 8844303.2 | J21: =$B21*J9 -> 11055379
A22: Tier 2 MSAs | B22: =SUMIF(MSAs!$I$2:$I$65,Users!B10,MSAs!$C$2:$C$65) -> 106210116 | D22: =$B22*D10 -> 0 | E22: =$B22*E10 -> 0 | F22: =$B22*F10 -> 0 | G22: =$B22*G10 -> 1062101.2 | H22: =$B22*H10 -> 5310505.8 | I22: =$B22*I10 -> 8496809.3 | J22: =$B22*J10 -> 15931517
A23: Tier 3 MSAs | B23: =MSAs!C70 -> 103228092 | D23: =$B23*D11 -> 0 | E23: =$B23*E11 -> 0 | F23: =$B23*F11 -> 0 | G23: =$B23*G11 -> 0 | H23: =$B23*H11 -> 1032280.9 | I23: =$B23*I11 -> 5161404.6 | J23: =$B23*J11 -> 8258247.4
A24: Total | B24: =SUM(B16:B23) -> 288609050
B26: New Users Acquired | D26: =SUM(D16:D23) -> 46176.11 | E26: =E27-D27 -> 57317.82 | F26: =F27-E27 -> 1045831.3 | G26: =G27-F27 -> 4273022.3 | H26: =H27-G27 -> 7906753 | I26: =I27-H27 -> 10511353 | J26: =J27-I27 -> 13124193
B27: Total Users Acquired | D27: =D26 -> 46176.11 | E27: =SUM(E16:E23) -> 103493.93 | F27: =SUM(F16:F23) -> 1149325.3 | G27: =SUM(G16:G23) -> 5422347.6 | H27: =SUM(H16:H23) -> 13329101 | I27: =SUM(I16:I23) -> 23840454 | J27: =SUM(J16:J23) -> 36964647

Sheet MSAs
A1: CBSA Code | B1: CBSA Title | C1: Population | D1: Total Merchants | E1: 71: Arts, Entertainment, & Recreation | F1: 722: Food Service & Drinking Places | G1: 44/45: Retail* | H1: 812: Personal and Laundry Services | I1: Launch Tier | J1: Launch Cost
A2: 14500 | B2: Boulder, CO | C2: 330758 | D2: =SUM(E2:H2) -> 2689.2 | E2: 308 | F2: 858 | G2: 1109.2 | H2: 414 | I2: 1 | J2: =C2*0.1 -> 33075.8
A3: 19740 | B3: Denver-Aurora-Lakewood, CO | C3: 2963821 | D3: =SUM(E3:H3) -> 19015.68 | E3: 1481 | F3: 6477 | G3: 8057.68 | H3: 3000 | I3: 2 | J3: =C3*0.1 -> 296382.1
A4: 17820 | B4: Colorado Springs, CO | C4: 755105 | D4: =SUM(E4:H4) -> 4172.58 | E4: 332 | F4: 1337 | G4: 1980.58 | H4: 523 | I4: 4 | J4: =C4*0.1 -> 75510.5
A5: 22660 | B5: Fort Collins, CO | C5: 359066 | D5: =SUM(E5:H5) -> 2536.64 | E5: 227 | F5: 826 | G5: 1180.64 | H5: 303 | I5: 3 | J5: =C5*0.1 -> 35906.6
A6: 24540 | B6: Greeley, CO | C6: 328981 | D6: =SUM(E6:H6) -> 1280.94 | E6: 71 | F6: 447 | G6: 611.94 | H6: 151 | I6: 5 | J6: =C6*0.1 -> 32898.1
A7: 39380 | B7: Pueblo, CO Metro Area | C7: 217101 | D7: =SUM(E7:H7) -> 897.24 | E7: 43 | F7: 303 | G7: 466.24 | H7: 85 | I7: 5 | J7: =C7*0.1 -> 21710.1
A8: 24300 | B8: Grand Junction, CO | C8: 155703 | D8: =SUM(E8:H8) -> 1002.92 | E8: 72 | F8: 283 | G8: 533.92 | H8: 114 | I8: 5 | J8: =C8*0.1 -> 15570.3
A9: 20780 | B9: Edwards, CO | C9: 134774 | D9: =SUM(E9:H9) -> 758.6 | E9: 75 | F9: 241 | G9: 366.6 | H9: 76 | I9: 5 | J9: =C9*0.1 -> 13477.4
A10: 20420 | B10: Durango, CO | C10: 55638 | D10: =SUM(E10:H10) -> 565.24 | E10: 58 | F10: 177 | G10: 278.24 | H10: 52 | I10: 5 | J10: =C10*0.1 -> 5563.8
A11: 33940 | B11: Montrose, CO | C11: 47553 | D11: =SUM(E11:H11) -> 269.86 | E11: 21 | F11: 73 | G11: 158.86 | H11: 17 | I11: 5 | J11: =C11*0.1 -> 4755.3
A12: 44460 | B12: Steamboat Springs, CO | C12: 38121 | D12: =SUM(E12:H12) -> 401.24 | E12: 56 | F12: 116 | G12: 184.24 | H12: 45 | I12: 5 | J12: =C12*0.1 -> 3812.1
A13: 14720 | B13: Breckenridge, CO | C13: 31055 | D13: =SUM(E13:H13) -> 623.64 | E13: 49 | F13: 228 | G13: 287.64 | H13: 59 | I13: 5 | J13: =C13*0.1 -> 3105.5
... A15: 44540 | B15: Sterling, CO | C15: 21528 | D15: =SUM(E15:H15) -> 141.9 | E15: 5 | F15: 42 | G15: 79.9 | H15: 15 | I15: 5 | J15: =C15*0.1 -> 2152.8
A16: 35620 | B16: New York-Newark-Jersey City, NY-NJ-PA | C16: 20140470 | D16: 173355 | E16: 13684 | F16: 53027 | G16: 72505.02 | H16: 29511 | I16: 6 | J16: =C16*0.1 -> 2014047
A17: 31080 | B17: Los Angeles-Long Beach-Anaheim, CA | C17: 13200998 | D17: 101189 | E17: 20327 | F17: 31001 | G17: 35970.04 | H17: 11595 | I17: 6 | J17: =C17*0.1 -> 1320099.8
A18: 16980 | B18: Chicago-Naperville-Elgin, IL-IN-WI | C18: 9618502 | D18: 59770 | E18: 4014 | F18: 20664 | G18: 24890.26 | H18: 8613 | I18: 6 | J18: =C18*0.1 -> 961850.2
A19: 19100 | B19: Dallas-Fort Worth-Arlington, TX | C19: 7637387 | D19: 42946 | E19: 2454 | F19: 15023 | G19: 19570.8 | H19: 4649 | I19: 7 | J19: =C19*0.1 -> 763738.7
A20: 26420 | B20: Houston-The Woodlands-Sugar Land, TX | C20: 7122240 | D20: 37747 | E20: 1805 | F20: 12974 | G20: 17704.9 | H20: 4133 | I20: 7 | J20: =C20*0.1 -> 712224
A21: 47900 | B21: Washington-Arlington-Alexandria, DC-VA-MD-WV | C21: 6385162 | D21: 36956 | E21: 2346 | F21: 13102 | G21: 14824.74 | H21: 5737 | I21: 6 | J21: =C21*0.1 -> 638516.2
A22: 37980 | B22: Philadelphia-Camden-Wilmington, PA-NJ-DE-MD | C22: 6245051 | D22: 41324 | E22: 2583 | F22: 13241 | G22: 17953.06 | H22: 6401 | I22: 6 | J22: =C22*0.1 -> 624505.1
A23: 12060 | B23: Atlanta-Sandy Springs-Alpharetta, GA | C23: 6089815 | D23: 37096 | E23: 2530 | F23: 12043 | G23: 16586.3 | H23: 4878 | I23: 7 | J23: =C23*0.1 -> 608981.5
A24: 33100 | B24: Miami-Fort Lauderdale-Pompano Beach, FL | C24: 6138333 | D24: 45241 | E24: 3340 | F24: 12283 | G24: 21761.94 | H24: 6467 | I24: 6 | J24: =C24*0.1 -> 613833.3
A25: 38060 | B25: Phoenix-Mesa-Chandler, AZ | C25: 4845832 | D25: 23991 | E25: 1573 | F25: 8225 | G25: 10595.68 | H25: 2921 | I25: 7 | J25: =C25*0.1 -> 484583.2
A26: 14460 | B26: Boston-Cambridge-Newton, MA-NH | C26: 4941632 | D26: 36588 | E26: 2636 | F26: 12216 | G26: 15136.82 | H26: 5633 | I26: 6 | J26: =C26*0.1 -> 494163.2
A27: 40140 | B27: Riverside-San Bernardino-Ontario, CA | C27: 4599839 | D27: 20925 | E27: 1143 | F27: 7392 | G27: 9595.52 | H27: 2182 | I27: 7 | J27: =C27*0.1 -> 459983.9
... A33: 45300 | B33: Tampa-St. Petersburg-Clearwater, FL | C33: 3175275 | D33: 19596 | E33: 1270 | F33: 5567 | G33: 9647.22 | H33: 2496 | I33: 7 | J33: =C33*0.1 -> 317527.5
A34: 19740 | B34: Denver-Aurora-Lakewood, CO | C34: 2963821 | D34: 19530 | E34: 1481 | F34: 6477 | G34: 8057.68 | H34: 3000 | I34: NA
A35: 12580 | B35: Baltimore-Columbia-Towson, MD | C35: 2844510 | D35: 17531 | E35: 1125 | F35: 5747 | G35: 8001.28 | H35: 2147 | I35: 7 | J35: =C35*0.1 -> 284451
A36: 41180 | B36: St. Louis, MO-IL | C36: 2820253 | D36: 17450 | E36: 1132 | F36: 5796 | G36: 8020.08 | H36: 1990 | I36: 7 | J36: =C36*0.1 -> 282025.3
A37: 16740 | B37: Charlotte-Concord-Gastonia, NC-SC | C37: 2660329 | D37: 15964 | E37: 1160 | F37: 5086 | G37: 7347.98 | H37: 1901 | I37: 7 | J37: =C37*0.1 -> 266032.9
A38: 36740 | B38: Orlando-Kissimmee-Sanford, FL | C38: 2673376 | D38: 17128 | E38: 1272 | F38: 5181 | G38: 8119.72 | H38: 2037 | I38: 7 | J38: =C38*0.1 -> 267337.6
A39: 41700 | B39: San Antonio-New Braunfels, TX | C39: 2558143 | D39: 12989 | E39: 697 | F39: 4578 | G39: 5883.46 | H39: 1455 | I39: 7 | J39: =C39*0.1 -> 255814.3
A40: 38900 | B40: Portland-Vancouver-Hillsboro, OR-WA | C40: 2512859 | D40: 16880 | E40: 1220 | F40: 6256 | G40: 6799.96 | H40: 2170 | I40: 7 | J40: =C40*0.1 -> 251285.9
A41: 40900 | B41: Sacramento-Roseville-Folsom, CA | C41: 2397382 | D41: 12882 | E41: 763 | F41: 4706 | G41: 5393.72 | H41: 1675 | I41: 7 | J41: =C41*0.1 -> 239738.2
A42: 38300 | B42: Pittsburgh, PA | C42: 2370930 | D42: 16497 | E42: 1080 | F42: 5323 | G42: 7265.26 | H42: 2365 | I42: 7 | J42: =C42*0.1 -> 237093
A43: 12420 | B43: Austin-Round Rock-Georgetown, TX | C43: 2283371 | D43: 13915 | E43: 1077 | F43: 4774 | G43: 5837.4 | H43: 1854 | I43: 6 | J43: =C43*0.1 -> 228337.1
A44: 29820 | B44: Las Vegas-Henderson-Paradise, NV | C44: 2265461 | D44: 13497 | E44: 1274 | F44: 4660 | G44: 5765.96 | H44: 1429 | I44: 7 | J44: =C44*0.1 -> 226546.1
A45: 17140 | B45: Cincinnati, OH-KY-IN | C45: 2256884 | D45: 12651 | E45: 755 | F45: 4227 | G45: 5812.02 | H45: 1486 | I45: 7 | J45: =C45*0.1 -> 225688.4
A46: 28140 | B46: Kansas City, MO-KS | C46: 2192035 | D46: 12317 | E46: 790 | F46: 3940 | G46: 5700.16 | H46: 1523 | I46: 7 | J46: =C46*0.1 -> 219203.5
... A65: 13820 | B65: Birmingham-Hoover, AL | C65: 1115289 | D65: 7170 | E65: 349 | F65: 2064 | G65: 3877.5 | H65: 632 | I65: 7 | J65: =C65*0.1 -> 111528.9
B67: Top 50 Totals | C67: =SUM(C16:C65) -> 182876464 | D67: 1192456 | E67: 94433 | F67: 391175 | G67: =SUM(G2:G65) -> 529077.12 | H67: 160366
E68: 0.08 | F68: 0.33 | G68: 0.46 | H68: 0.13
B70: Remaining MSAs | C70: 103228092 | D70: =D73-D67 -> 806800 | E70: =E73-E67 -> 49471 | F70: =F73-F67 -> 249631 | G70: =G73-G67 -> 389514.88 | H70: =H73-H67 -> 76954 | I70: 8 | J70: =C70*0.1 -> 10322809
E71: =E70/$D$70 -> 0.061317551 | F71: =F70/$D$70 -> 0.30940878 | G71: =G70/$D$70 -> 0.48278989 | H71: =H70/$D$70 -> 0.095381755
B73: All MSAs | C73: =C67+C70 -> 286104556 | D73: 1999256 | E73: 143904 | F73: 640806 | G73: 918592 | H73: 237320
E74: 0.07 | F74: 0.32 | G74: 0.49 | H74: 0.12
A75: Source: US Census 2020, U.S. Bureau of Labor Statistics
A76: *Remove 6% for Nonstore Retailers: NAICS 454
